{
  "teamId": "texasam",
  "teamSlug": "texas-am-aggies",
  "teamName": "Texas A&M Aggies",
  "draftPicks": [
    {
      "year": 2025,
      "round": 1,
      "pick": 17,
      "name": "Shemar Stewart",
      "position": "DE",
      "nflTeam": "Cincinnati Bengals"
    },
    {
      "year": 2025,
      "round": 2,
      "pick": 51,
      "name": "Nic Scourton",
      "position": "DE",
      "nflTeam": "Carolina Panthers"
    },
    {
      "year": 2025,
      "round": 2,
      "pick": 62,
      "name": "Shemar Turner",
      "position": "DE",
      "nflTeam": "Chicago Bears"
    },
    {
      "year": 2024,
      "round": 2,
      "pick": 45,
      "name": "Edgerrin Cooper",
      "position": "LB",
      "nflTeam": "Green Bay Packers"
    },
    {
      "year": 2024,
      "round": 3,
      "pick": 97,
      "name": "McKinnley Jackson",
      "position": "DL",
      "nflTeam": "Cincinnati Bengals"
    },
    {
      "year": 2024,
      "round": 4,
      "pick": 103,
      "name": "Layden Robinson",
      "position": "OL",
      "nflTeam": "New England Patriots"
    },
    {
      "year": 2024,
      "round": 5,
      "pick": 152,
      "name": "Ainias Smith",
      "position": "WR",
      "nflTeam": "Philadelphia Eagles"
    },
    {
      "year": 2023,
      "round": 3,
      "pick": 84,
      "name": "De'Von Achane",
      "position": "RB",
      "nflTeam": "Miami Dolphins"
    },
    {
      "year": 2023,
      "round": 5,
      "pick": 160,
      "name": "Antonio Johnson",
      "position": "DB",
      "nflTeam": "Jacksonville Jaguars"
    },
    {
      "year": 2023,
      "round": 7,
      "pick": 221,
      "name": "Jaylon Jones",
      "position": "DB",
      "nflTeam": "Indianapolis Colts"
    },
    {
      "year": 2022,
      "round": 1,
      "pick": 15,
      "name": "Kenyon Green",
      "position": "OL",
      "nflTeam": "Houston Texans"
    },
    {
      "year": 2022,
      "round": 3,
      "pick": 84,
      "name": "DeMarvin Leal",
      "position": "DT",
      "nflTeam": "Pittsburgh Steelers"
    },
    {
      "year": 2022,
      "round": 4,
      "pick": 117,
      "name": "Micheal Clemons",
      "position": "DT",
      "nflTeam": "New York Jets"
    },
    {
      "year": 2022,
      "round": 4,
      "pick": 123,
      "name": "Isaiah Spiller",
      "position": "RB",
      "nflTeam": "Los Angeles Chargers"
    },
    {
      "year": 2021,
      "round": 3,
      "pick": 66,
      "name": "Kellen Mond",
      "position": "QB",
      "nflTeam": "Minnesota Vikings"
    },
    {
      "year": 2021,
      "round": 4,
      "pick": 117,
      "name": "Bobby Brown",
      "position": "DL",
      "nflTeam": "Los Angeles Rams"
    },
    {
      "year": 2021,
      "round": 4,
      "pick": 128,
      "name": "Dan Moore",
      "position": "OL",
      "nflTeam": "Pittsburgh Steelers"
    },
    {
      "year": 2021,
      "round": 4,
      "pick": 140,
      "name": "Buddy Johnson",
      "position": "LB",
      "nflTeam": "Pittsburgh Steelers"
    },
    {
      "year": 2020,
      "round": 3,
      "pick": 71,
      "name": "Nnamdi Madubuike",
      "position": "DT",
      "nflTeam": "Baltimore Ravens"
    },
    {
      "year": 2020,
      "round": 6,
      "pick": 191,
      "name": "Braden Mann",
      "position": "P",
      "nflTeam": "New York Jets"
    },
    {
      "year": 2019,
      "round": 2,
      "pick": 48,
      "name": "Erik McCoy",
      "position": "C",
      "nflTeam": "New Orleans Saints"
    },
    {
      "year": 2019,
      "round": 3,
      "pick": 75,
      "name": "Jace Sternberger",
      "position": "TE",
      "nflTeam": "Green Bay Packers"
    },
    {
      "year": 2019,
      "round": 5,
      "pick": 150,
      "name": "Kingsley Keke",
      "position": "DT",
      "nflTeam": "Green Bay Packers"
    },
    {
      "year": 2019,
      "round": 5,
      "pick": 160,
      "name": "Daylon Mack",
      "position": "DT",
      "nflTeam": "Baltimore Ravens"
    },
    {
      "year": 2019,
      "round": 6,
      "pick": 182,
      "name": "Trayveon Williams",
      "position": "RB",
      "nflTeam": "Cincinnati Bengals"
    },
    {
      "year": 2019,
      "round": 6,
      "pick": 213,
      "name": "Donovan Wilson",
      "position": "S",
      "nflTeam": "Dallas Cowboys"
    },
    {
      "year": 2019,
      "round": 7,
      "pick": 220,
      "name": "Cullen Gillaspia",
      "position": "RB",
      "nflTeam": "Houston Texans"
    },
    {
      "year": 2018,
      "round": 2,
      "pick": 47,
      "name": "Christian Kirk",
      "position": "WR",
      "nflTeam": "Arizona Cardinals"
    },
    {
      "year": 2018,
      "round": 4,
      "pick": 124,
      "name": "Armani Watts",
      "position": "S",
      "nflTeam": "Kansas City Chiefs"
    },
    {
      "year": 2018,
      "round": 6,
      "pick": 175,
      "name": "Damion Ratley",
      "position": "WR",
      "nflTeam": "Cleveland Browns"
    },
    {
      "year": 2017,
      "round": 1,
      "pick": 1,
      "name": "Myles Garrett",
      "position": "DE",
      "nflTeam": "Cleveland Browns"
    },
    {
      "year": 2017,
      "round": 2,
      "pick": 50,
      "name": "Justin Evans",
      "position": "S",
      "nflTeam": "Tampa Bay Buccaneers"
    },
    {
      "year": 2017,
      "round": 3,
      "pick": 77,
      "name": "Daeshon Hall",
      "position": "DE",
      "nflTeam": "Carolina Panthers"
    },
    {
      "year": 2017,
      "round": 4,
      "pick": 117,
      "name": "Josh Reynolds",
      "position": "WR",
      "nflTeam": "Los Angeles Rams"
    },
    {
      "year": 2017,
      "round": 5,
      "pick": 159,
      "name": "Jermaine Eluemunor",
      "position": "G",
      "nflTeam": "Baltimore Ravens"
    },
    {
      "year": 2016,
      "round": 1,
      "pick": 31,
      "name": "Germain Ifedi",
      "position": "G",
      "nflTeam": "Seattle Seahawks"
    },
    {
      "year": 2016,
      "round": 3,
      "pick": 92,
      "name": "Brandon Williams",
      "position": "CB",
      "nflTeam": "Arizona Cardinals"
    },
    {
      "year": 2016,
      "round": 6,
      "pick": 179,
      "name": "Drew Kaser",
      "position": "P",
      "nflTeam": "San Diego Chargers"
    },
    {
      "year": 2015,
      "round": 1,
      "pick": 21,
      "name": "Cedric Ogbuehi",
      "position": "T",
      "nflTeam": "Cincinnati Bengals"
    },
    {
      "year": 2015,
      "round": 5,
      "pick": 152,
      "name": "Jarvis Harrison",
      "position": "G",
      "nflTeam": "New York Jets"
    },
    {
      "year": 2014,
      "round": 1,
      "pick": 6,
      "name": "Jake Matthews",
      "position": "T",
      "nflTeam": "Atlanta Falcons"
    },
    {
      "year": 2014,
      "round": 1,
      "pick": 7,
      "name": "Mike Evans",
      "position": "WR",
      "nflTeam": "Tampa Bay Buccaneers"
    },
    {
      "year": 2014,
      "round": 1,
      "pick": 22,
      "name": "Johnny Manziel",
      "position": "QB",
      "nflTeam": "Cleveland Browns"
    },
    {
      "year": 2013,
      "round": 1,
      "pick": 2,
      "name": "Luke Joeckel",
      "position": "T",
      "nflTeam": "Jacksonville Jaguars"
    },
    {
      "year": 2013,
      "round": 2,
      "pick": 62,
      "name": "Christine Michael",
      "position": "RB",
      "nflTeam": "Seattle Seahawks"
    },
    {
      "year": 2013,
      "round": 3,
      "pick": 81,
      "name": "Damontre Moore",
      "position": "DE",
      "nflTeam": "New York Giants"
    },
    {
      "year": 2013,
      "round": 4,
      "pick": 118,
      "name": "Sean Porter",
      "position": "LB",
      "nflTeam": "Cincinnati Bengals"
    },
    {
      "year": 2013,
      "round": 6,
      "pick": 174,
      "name": "Ryan Swope",
      "position": "WR",
      "nflTeam": "Arizona Cardinals"
    },
    {
      "year": 2012,
      "round": 1,
      "pick": 8,
      "name": "Ryan Tannehill",
      "position": "QB",
      "nflTeam": "Miami Dolphins"
    },
    {
      "year": 2012,
      "round": 5,
      "pick": 161,
      "name": "Randy Bullock",
      "position": "K",
      "nflTeam": "Houston Texans"
    },
    {
      "year": 2012,
      "round": 6,
      "pick": 182,
      "name": "Cyrus Gray",
      "position": "RB",
      "nflTeam": "Kansas City Chiefs"
    },
    {
      "year": 2012,
      "round": 7,
      "pick": 246,
      "name": "Terrence Frederick",
      "position": "DB",
      "nflTeam": "Pittsburgh Steelers"
    },
    {
      "year": 2011,
      "round": 1,
      "pick": 2,
      "name": "Von Miller",
      "position": "LB",
      "nflTeam": "Denver Broncos"
    },
    {
      "year": 2010,
      "round": 6,
      "pick": 202,
      "name": "Jordan Pugh",
      "position": "DB",
      "nflTeam": "Carolina Panthers"
    },
    {
      "year": 2009,
      "round": 4,
      "pick": 101,
      "name": "Stephen McGee",
      "position": "QB",
      "nflTeam": "Dallas Cowboys"
    },
    {
      "year": 2009,
      "round": 4,
      "pick": 111,
      "name": "Mike Goodson",
      "position": "RB",
      "nflTeam": "Carolina Panthers"
    },
    {
      "year": 2008,
      "round": 2,
      "pick": 61,
      "name": "Martellus Bennett",
      "position": "TE",
      "nflTeam": "Dallas Cowboys"
    },
    {
      "year": 2008,
      "round": 4,
      "pick": 107,
      "name": "Cody Wallace",
      "position": "C",
      "nflTeam": "San Francisco 49ers"
    },
    {
      "year": 2008,
      "round": 4,
      "pick": 121,
      "name": "Red Bryant",
      "position": "DT",
      "nflTeam": "Seattle Seahawks"
    },
    {
      "year": 2008,
      "round": 6,
      "pick": 185,
      "name": "Chris Harrington",
      "position": "DE",
      "nflTeam": "Arizona Cardinals"
    },
    {
      "year": 2008,
      "round": 7,
      "pick": 234,
      "name": "Corey Clark",
      "position": "T",
      "nflTeam": "San Diego Chargers"
    },
    {
      "year": 2006,
      "round": 6,
      "pick": 183,
      "name": "Johnny Jolly",
      "position": "DT",
      "nflTeam": "Green Bay Packers"
    },
    {
      "year": 2006,
      "round": 6,
      "pick": 193,
      "name": "Reggie McNeal",
      "position": "QB",
      "nflTeam": "Cincinnati Bengals"
    },
    {
      "year": 2005,
      "round": 2,
      "pick": 58,
      "name": "Terrence Murphy",
      "position": "WR",
      "nflTeam": "Green Bay Packers"
    },
    {
      "year": 2005,
      "round": 5,
      "pick": 169,
      "name": "Geoff Hangartner",
      "position": "C",
      "nflTeam": "Carolina Panthers"
    },
    {
      "year": 2005,
      "round": 6,
      "pick": 180,
      "name": "Mike Montgomery",
      "position": "DT",
      "nflTeam": "Green Bay Packers"
    },
    {
      "year": 2004,
      "round": 6,
      "pick": 168,
      "name": "Jamaar Taylor",
      "position": "WR",
      "nflTeam": "New York Giants"
    },
    {
      "year": 2003,
      "round": 1,
      "pick": 13,
      "name": "Ty Warren",
      "position": "DE",
      "nflTeam": "New England Patriots"
    },
    {
      "year": 2003,
      "round": 1,
      "pick": 30,
      "name": "Sammy Davis",
      "position": "DB",
      "nflTeam": "San Diego Chargers"
    },
    {
      "year": 2003,
      "round": 2,
      "pick": 45,
      "name": "Bethel Johnson",
      "position": "WR",
      "nflTeam": "New England Patriots"
    },
    {
      "year": 2003,
      "round": 2,
      "pick": 62,
      "name": "Terrence Kiel",
      "position": "DB",
      "nflTeam": "San Diego Chargers"
    },
    {
      "year": 2003,
      "round": 3,
      "pick": 87,
      "name": "Taylor Whitley",
      "position": "G",
      "nflTeam": "Miami Dolphins"
    },
    {
      "year": 2002,
      "round": 3,
      "pick": 90,
      "name": "Seth McKinney",
      "position": "C",
      "nflTeam": "Miami Dolphins"
    },
    {
      "year": 2002,
      "round": 5,
      "pick": 146,
      "name": "Rocky Bernard",
      "position": "DT",
      "nflTeam": "Seattle Seahawks"
    },
    {
      "year": 2001,
      "round": 2,
      "pick": 41,
      "name": "Robert Ferguson",
      "position": "WR",
      "nflTeam": "Green Bay Packers"
    },
    {
      "year": 2001,
      "round": 3,
      "pick": 76,
      "name": "Ron Edwards",
      "position": "DT",
      "nflTeam": "Buffalo Bills"
    },
    {
      "year": 2001,
      "round": 6,
      "pick": 165,
      "name": "Michael Jameson",
      "position": "DB",
      "nflTeam": "Cleveland Browns"
    },
    {
      "year": 2001,
      "round": 6,
      "pick": 173,
      "name": "Jason Glenn",
      "position": "LB",
      "nflTeam": "Detroit Lions"
    },
    {
      "year": 2001,
      "round": 7,
      "pick": 218,
      "name": "Chris Taylor",
      "position": "WR",
      "nflTeam": "Pittsburgh Steelers"
    },
    {
      "year": 2001,
      "round": 7,
      "pick": 226,
      "name": "Ronald Flemons",
      "position": "DE",
      "nflTeam": "Atlanta Falcons"
    },
    {
      "year": 2000,
      "round": 2,
      "pick": 48,
      "name": "Jason Webster",
      "position": "DB",
      "nflTeam": "San Francisco 49ers"
    },
    {
      "year": 2000,
      "round": 3,
      "pick": 70,
      "name": "Chris Cole",
      "position": "WR",
      "nflTeam": "Denver Broncos"
    },
    {
      "year": 2000,
      "round": 5,
      "pick": 142,
      "name": "Shane Lechler",
      "position": "P",
      "nflTeam": "Oakland Raiders"
    },
    {
      "year": 2000,
      "round": 5,
      "pick": 153,
      "name": "Dante Hall",
      "position": "WR",
      "nflTeam": "Kansas City Chiefs"
    },
    {
      "year": 1999,
      "round": 3,
      "pick": 66,
      "name": "Rex Tucker",
      "position": "G",
      "nflTeam": "Chicago Bears"
    },
    {
      "year": 1999,
      "round": 3,
      "pick": 68,
      "name": "Rich Coady",
      "position": "DB",
      "nflTeam": "St. Louis Rams"
    },
    {
      "year": 1999,
      "round": 3,
      "pick": 79,
      "name": "Dan Campbell",
      "position": "TE",
      "nflTeam": "New York Giants"
    },
    {
      "year": 1999,
      "round": 3,
      "pick": 85,
      "name": "Dat Nguyen",
      "position": "LB",
      "nflTeam": "Dallas Cowboys"
    },
    {
      "year": 1999,
      "round": 4,
      "pick": 106,
      "name": "Warrick Holdman",
      "position": "LB",
      "nflTeam": "Chicago Bears"
    },
    {
      "year": 1999,
      "round": 5,
      "pick": 145,
      "name": "Cameron Spikes",
      "position": "G",
      "nflTeam": "St. Louis Rams"
    },
    {
      "year": 1998,
      "round": 3,
      "pick": 89,
      "name": "Chris Ruhman",
      "position": "T",
      "nflTeam": "San Francisco 49ers"
    },
    {
      "year": 1998,
      "round": 4,
      "pick": 93,
      "name": "Steve McKinney",
      "position": "C",
      "nflTeam": "Indianapolis Colts"
    },
    {
      "year": 1997,
      "round": 2,
      "pick": 59,
      "name": "Brandon Mitchell",
      "position": "DE",
      "nflTeam": "New England Patriots"
    },
    {
      "year": 1997,
      "round": 4,
      "pick": 115,
      "name": "Albert Connell",
      "position": "WR",
      "nflTeam": "Washington Redskins"
    },
    {
      "year": 1997,
      "round": 6,
      "pick": 180,
      "name": "Calvin Collins",
      "position": "G",
      "nflTeam": "Atlanta Falcons"
    },
    {
      "year": 1997,
      "round": 6,
      "pick": 198,
      "name": "Ed Jasper",
      "position": "DT",
      "nflTeam": "Philadelphia Eagles"
    },
    {
      "year": 1996,
      "round": 1,
      "pick": 17,
      "name": "Reggie Brown",
      "position": "LB",
      "nflTeam": "Detroit Lions"
    },
    {
      "year": 1996,
      "round": 2,
      "pick": 32,
      "name": "Leeland McElroy",
      "position": "RB",
      "nflTeam": "Arizona Cardinals"
    },
    {
      "year": 1996,
      "round": 3,
      "pick": 62,
      "name": "Ray Mickens",
      "position": "DB",
      "nflTeam": "New York Jets"
    },
    {
      "year": 1996,
      "round": 3,
      "pick": 65,
      "name": "Detron Smith",
      "position": "RB",
      "nflTeam": "Denver Broncos"
    },
    {
      "year": 1996,
      "round": 4,
      "pick": 97,
      "name": "Hunter Goodwin",
      "position": "TE",
      "nflTeam": "Minnesota Vikings"
    },
    {
      "year": 1996,
      "round": 6,
      "pick": 201,
      "name": "Hayward Clay",
      "position": "TE",
      "nflTeam": "St. Louis Rams"
    },
    {
      "year": 1995,
      "round": 3,
      "pick": 89,
      "name": "Rodney Thomas",
      "position": "RB",
      "nflTeam": "Houston Oilers"
    },
    {
      "year": 1995,
      "round": 6,
      "pick": 201,
      "name": "Antonio Armstrong",
      "position": "LB",
      "nflTeam": "San Francisco 49ers"
    },
    {
      "year": 1994,
      "round": 1,
      "pick": 8,
      "name": "Sam Adams",
      "position": "DT",
      "nflTeam": "Seattle Seahawks"
    },
    {
      "year": 1994,
      "round": 1,
      "pick": 12,
      "name": "Aaron Glenn",
      "position": "DB",
      "nflTeam": "New York Jets"
    },
    {
      "year": 1994,
      "round": 1,
      "pick": 25,
      "name": "Greg Hill",
      "position": "RB",
      "nflTeam": "Kansas City Chiefs"
    },
    {
      "year": 1994,
      "round": 3,
      "pick": 67,
      "name": "Jason Mathews",
      "position": "T",
      "nflTeam": "Indianapolis Colts"
    },
    {
      "year": 1994,
      "round": 3,
      "pick": 89,
      "name": "Eric England",
      "position": "DE",
      "nflTeam": "Arizona Cardinals"
    },
    {
      "year": 1994,
      "round": 7,
      "pick": 196,
      "name": "Lance Teichelman",
      "position": "DE",
      "nflTeam": "Indianapolis Colts"
    },
    {
      "year": 1993,
      "round": 1,
      "pick": 12,
      "name": "Patrick Bates",
      "position": "DB",
      "nflTeam": "Los Angeles Raiders"
    },
    {
      "year": 1993,
      "round": 3,
      "pick": 66,
      "name": "Marcus Buckley",
      "position": "LB",
      "nflTeam": "New York Giants"
    },
    {
      "year": 1993,
      "round": 3,
      "pick": 75,
      "name": "Derrick Frazier",
      "position": "DB",
      "nflTeam": "Philadelphia Eagles"
    },
    {
      "year": 1992,
      "round": 1,
      "pick": 2,
      "name": "Quentin Coryatt",
      "position": "LB",
      "nflTeam": "Indianapolis Colts"
    },
    {
      "year": 1992,
      "round": 1,
      "pick": 17,
      "name": "Kevin Smith",
      "position": "DB",
      "nflTeam": "Dallas Cowboys"
    },
    {
      "year": 1992,
      "round": 3,
      "pick": 59,
      "name": "Mark Wheeler",
      "position": "DT",
      "nflTeam": "Tampa Bay Buccaneers"
    },
    {
      "year": 1992,
      "round": 5,
      "pick": 114,
      "name": "Chris Crooms",
      "position": "DB",
      "nflTeam": "Los Angeles Rams"
    },
    {
      "year": 1992,
      "round": 8,
      "pick": 220,
      "name": "Bucky Richardson",
      "position": "QB",
      "nflTeam": "Houston Oilers"
    },
    {
      "year": 1992,
      "round": 9,
      "pick": 243,
      "name": "Keith Alex",
      "position": "G",
      "nflTeam": "Atlanta Falcons"
    },
    {
      "year": 1991,
      "round": 3,
      "pick": 80,
      "name": "Robert Wilson",
      "position": "RB",
      "nflTeam": "Tampa Bay Buccaneers"
    },
    {
      "year": 1991,
      "round": 4,
      "pick": 104,
      "name": "William Thomas",
      "position": "LB",
      "nflTeam": "Philadelphia Eagles"
    },
    {
      "year": 1991,
      "round": 5,
      "pick": 130,
      "name": "Mike Arthur",
      "position": "C",
      "nflTeam": "Cincinnati Bengals"
    },
    {
      "year": 1991,
      "round": 6,
      "pick": 161,
      "name": "Darren Lewis",
      "position": "RB",
      "nflTeam": "Chicago Bears"
    },
    {
      "year": 1991,
      "round": 9,
      "pick": 241,
      "name": "Shane Garrett",
      "position": "WR",
      "nflTeam": "Cincinnati Bengals"
    },
    {
      "year": 1990,
      "round": 1,
      "pick": 9,
      "name": "Richmond Webb",
      "position": "T",
      "nflTeam": "Miami Dolphins"
    },
    {
      "year": 1990,
      "round": 2,
      "pick": 37,
      "name": "Aaron Wallace",
      "position": "LB",
      "nflTeam": "Los Angeles Raiders"
    },
    {
      "year": 1990,
      "round": 3,
      "pick": 54,
      "name": "Mike Jones",
      "position": "TE",
      "nflTeam": "Minnesota Vikings"
    },
    {
      "year": 1990,
      "round": 4,
      "pick": 82,
      "name": "Jeroy Robinson",
      "position": "LB",
      "nflTeam": "Denver Broncos"
    },
    {
      "year": 1990,
      "round": 4,
      "pick": 106,
      "name": "Rick Cunningham",
      "position": "T",
      "nflTeam": "Indianapolis Colts"
    },
    {
      "year": 1990,
      "round": 8,
      "pick": 199,
      "name": "Mickey Washington",
      "position": "DB",
      "nflTeam": "Phoenix Cardinals"
    },
    {
      "year": 1990,
      "round": 9,
      "pick": 239,
      "name": "Gary Jones",
      "position": "DB",
      "nflTeam": "Pittsburgh Steelers"
    },
    {
      "year": 1990,
      "round": 10,
      "pick": 255,
      "name": "Terry Price",
      "position": "DE",
      "nflTeam": "Chicago Bears"
    },
    {
      "year": 1989,
      "round": 2,
      "pick": 36,
      "name": "John Roper",
      "position": "LB",
      "nflTeam": "Chicago Bears"
    },
    {
      "year": 1989,
      "round": 3,
      "pick": 65,
      "name": "Jerry Fontenot",
      "position": "C",
      "nflTeam": "Chicago Bears"
    },
    {
      "year": 1989,
      "round": 4,
      "pick": 104,
      "name": "Rod Harris",
      "position": "WR",
      "nflTeam": "Houston Oilers"
    },
    {
      "year": 1989,
      "round": 10,
      "pick": 265,
      "name": "Adam Bob",
      "position": "LB",
      "nflTeam": "New York Jets"
    },
    {
      "year": 1988,
      "round": 3,
      "pick": 61,
      "name": "Keith Woodside",
      "position": "RB",
      "nflTeam": "Green Bay Packers"
    },
    {
      "year": 1988,
      "round": 8,
      "pick": 220,
      "name": "Louis Cheek",
      "position": "T",
      "nflTeam": "Miami Dolphins"
    },
    {
      "year": 1988,
      "round": 9,
      "pick": 223,
      "name": "Kip Corrington",
      "position": "DB",
      "nflTeam": "Detroit Lions"
    },
    {
      "year": 1988,
      "round": 11,
      "pick": 303,
      "name": "Chet Brooks",
      "position": "DB",
      "nflTeam": "San Francisco 49ers"
    },
    {
      "year": 1987,
      "round": 1,
      "pick": 21,
      "name": "Roger Vick",
      "position": "RB",
      "nflTeam": "New York Jets"
    },
    {
      "year": 1987,
      "round": 1,
      "pick": 24,
      "name": "Rod Bernstine",
      "position": "RB",
      "nflTeam": "San Diego Chargers"
    },
    {
      "year": 1987,
      "round": 2,
      "pick": 41,
      "name": "Johnny Holland",
      "position": "LB",
      "nflTeam": "Green Bay Packers"
    },
    {
      "year": 1987,
      "round": 3,
      "pick": 73,
      "name": "Todd Howard",
      "position": "LB",
      "nflTeam": "Kansas City Chiefs"
    },
    {
      "year": 1987,
      "round": 4,
      "pick": 90,
      "name": "Rod Saddler",
      "position": "DT",
      "nflTeam": "St. Louis Cardinals"
    },
    {
      "year": 1987,
      "round": 4,
      "pick": 108,
      "name": "Larry Kelm",
      "position": "LB",
      "nflTeam": "Los Angeles Rams"
    },
    {
      "year": 1987,
      "round": 12,
      "pick": 314,
      "name": "Ira Valentine",
      "position": "RB",
      "nflTeam": "Houston Oilers"
    },
    {
      "year": 1986,
      "round": 2,
      "pick": 37,
      "name": "Anthony Toney",
      "position": "RB",
      "nflTeam": "Philadelphia Eagles"
    },
    {
      "year": 1986,
      "round": 2,
      "pick": 49,
      "name": "Doug Williams",
      "position": "T",
      "nflTeam": "New York Jets"
    },
    {
      "year": 1986,
      "round": 4,
      "pick": 106,
      "name": "Matt Darwin",
      "position": "T",
      "nflTeam": "Philadelphia Eagles"
    },
    {
      "year": 1986,
      "round": 6,
      "pick": 148,
      "name": "Domingo Bryant",
      "position": "DB",
      "nflTeam": "Pittsburgh Steelers"
    },
    {
      "year": 1985,
      "round": 1,
      "pick": 3,
      "name": "Ray Childress",
      "position": "DT",
      "nflTeam": "Houston Oilers"
    },
    {
      "year": 1985,
      "round": 5,
      "pick": 130,
      "name": "Jimmy Teal",
      "position": "WR",
      "nflTeam": "Buffalo Bills"
    },
    {
      "year": 1985,
      "round": 6,
      "pick": 155,
      "name": "Mark Lewis",
      "position": "TE",
      "nflTeam": "Green Bay Packers"
    },
    {
      "year": 1985,
      "round": 6,
      "pick": 156,
      "name": "Ken Reeves",
      "position": "T",
      "nflTeam": "Philadelphia Eagles"
    },
    {
      "year": 1985,
      "round": 9,
      "pick": 250,
      "name": "Thomas Sanders",
      "position": "RB",
      "nflTeam": "Chicago Bears"
    },
    {
      "year": 1984,
      "round": 1,
      "pick": 25,
      "name": "Billy Cannon",
      "position": "LB",
      "nflTeam": "Dallas Cowboys"
    },
    {
      "year": 1984,
      "round": 5,
      "pick": 134,
      "name": "Jeff Paine",
      "position": "LB",
      "nflTeam": "Kansas City Chiefs"
    },
    {
      "year": 1984,
      "round": 5,
      "pick": 139,
      "name": "Jeff Fuller",
      "position": "DB",
      "nflTeam": "San Francisco 49ers"
    },
    {
      "year": 1984,
      "round": 6,
      "pick": 144,
      "name": "Keith Guthrie",
      "position": "NT",
      "nflTeam": "San Diego Chargers"
    },
    {
      "year": 1983,
      "round": 2,
      "pick": 51,
      "name": "Johnny Hector",
      "position": "RB",
      "nflTeam": "New York Jets"
    },
    {
      "year": 1983,
      "round": 8,
      "pick": 197,
      "name": "Gary Kubiak",
      "position": "QB",
      "nflTeam": "Denver Broncos"
    },
    {
      "year": 1983,
      "round": 8,
      "pick": 202,
      "name": "Earnest Jackson",
      "position": "RB",
      "nflTeam": "San Diego Chargers"
    },
    {
      "year": 1982,
      "round": 2,
      "pick": 31,
      "name": "Keith Baldwin",
      "position": "DE",
      "nflTeam": "Cleveland Browns"
    },
    {
      "year": 1982,
      "round": 6,
      "pick": 162,
      "name": "Mike Whitwell",
      "position": "DB",
      "nflTeam": "Cleveland Browns"
    },
    {
      "year": 1981,
      "round": 3,
      "pick": 76,
      "name": "Mike Mosley",
      "position": "WR",
      "nflTeam": "Buffalo Bills"
    },
    {
      "year": 1981,
      "round": 6,
      "pick": 152,
      "name": "Mack Moore",
      "position": "DE",
      "nflTeam": "Miami Dolphins"
    },
    {
      "year": 1980,
      "round": 1,
      "pick": 5,
      "name": "Curtis Dickey",
      "position": "RB",
      "nflTeam": "Baltimore Colts"
    },
    {
      "year": 1980,
      "round": 1,
      "pick": 10,
      "name": "Jacob Green",
      "position": "DE",
      "nflTeam": "Seattle Seahawks"
    },
    {
      "year": 1980,
      "round": 9,
      "pick": 240,
      "name": "Gerald Carter",
      "position": "WR",
      "nflTeam": "Tampa Bay Buccaneers"
    },
    {
      "year": 1979,
      "round": 3,
      "pick": 74,
      "name": "Tony Franklin",
      "position": "K",
      "nflTeam": "Philadelphia Eagles"
    },
    {
      "year": 1979,
      "round": 7,
      "pick": 183,
      "name": "Cody Risien",
      "position": "T",
      "nflTeam": "Cleveland Browns"
    },
    {
      "year": 1979,
      "round": 8,
      "pick": 217,
      "name": "Gene Sanders",
      "position": "T",
      "nflTeam": "Tampa Bay Buccaneers"
    },
    {
      "year": 1978,
      "round": 5,
      "pick": 117,
      "name": "Frank Myers",
      "position": "T",
      "nflTeam": "Baltimore Colts"
    },
    {
      "year": 1978,
      "round": 10,
      "pick": 274,
      "name": "Mark Dennard",
      "position": "C",
      "nflTeam": "Miami Dolphins"
    },
    {
      "year": 1977,
      "round": 1,
      "pick": 17,
      "name": "Robert Jackson",
      "position": "LB",
      "nflTeam": "Cleveland Browns"
    },
    {
      "year": 1977,
      "round": 2,
      "pick": 55,
      "name": "Dennis Swilley",
      "position": "C",
      "nflTeam": "Minnesota Vikings"
    },
    {
      "year": 1977,
      "round": 3,
      "pick": 63,
      "name": "Edgar Fields",
      "position": "DT",
      "nflTeam": "Atlanta Falcons"
    },
    {
      "year": 1977,
      "round": 3,
      "pick": 72,
      "name": "Tank Marshall",
      "position": "DT",
      "nflTeam": "New York Jets"
    },
    {
      "year": 1977,
      "round": 4,
      "pick": 86,
      "name": "Jimmy Dean",
      "position": "DE",
      "nflTeam": "Buffalo Bills"
    },
    {
      "year": 1977,
      "round": 5,
      "pick": 126,
      "name": "Lester Hayes",
      "position": "DB",
      "nflTeam": "Oakland Raiders"
    },
    {
      "year": 1976,
      "round": 1,
      "pick": 9,
      "name": "Bubba Bean",
      "position": "RB",
      "nflTeam": "Atlanta Falcons"
    },
    {
      "year": 1976,
      "round": 2,
      "pick": 38,
      "name": "Glenn Bujnoch",
      "position": "G",
      "nflTeam": "Cincinnati Bengals"
    },
    {
      "year": 1976,
      "round": 2,
      "pick": 39,
      "name": "Pat Thomas",
      "position": "DB",
      "nflTeam": "Los Angeles Rams"
    },
    {
      "year": 1976,
      "round": 3,
      "pick": 81,
      "name": "Ed Simonini",
      "position": "LB",
      "nflTeam": "Baltimore Colts"
    },
    {
      "year": 1976,
      "round": 7,
      "pick": 198,
      "name": "Garth Ten Napel",
      "position": "LB",
      "nflTeam": "Detroit Lions"
    },
    {
      "year": 1976,
      "round": 9,
      "pick": 248,
      "name": "Richard Osborne",
      "position": "TE",
      "nflTeam": "Philadelphia Eagles"
    },
    {
      "year": 1976,
      "round": 14,
      "pick": 377,
      "name": "Carl Roaches",
      "position": "WR",
      "nflTeam": "Tampa Bay Buccaneers"
    },
    {
      "year": 1975,
      "round": 1,
      "pick": 21,
      "name": "Tim Gray",
      "position": "DB",
      "nflTeam": "St. Louis Cardinals"
    },
    {
      "year": 1975,
      "round": 5,
      "pick": 115,
      "name": "John McCrumbly",
      "position": "LB",
      "nflTeam": "Buffalo Bills"
    },
    {
      "year": 1973,
      "round": 3,
      "pick": 56,
      "name": "Brad Dusek",
      "position": "LB",
      "nflTeam": "New England Patriots"
    },
    {
      "year": 1972,
      "round": 2,
      "pick": 33,
      "name": "Kelvin Korver",
      "position": "DT",
      "nflTeam": "Oakland Raiders"
    },
    {
      "year": 1971,
      "round": 3,
      "pick": 63,
      "name": "Dave Elmendorf",
      "position": "DB",
      "nflTeam": "Los Angeles Rams"
    },
    {
      "year": 1970,
      "round": 1,
      "pick": 8,
      "name": "Larry Stegent",
      "position": "RB",
      "nflTeam": "St. Louis Cardinals"
    },
    {
      "year": 1970,
      "round": 4,
      "pick": 100,
      "name": "Ross Brupbacher",
      "position": "LB",
      "nflTeam": "Chicago Bears"
    },
    {
      "year": 1969,
      "round": 2,
      "pick": 35,
      "name": "Rolf Krueger",
      "position": "DE",
      "nflTeam": "St. Louis Cardinals"
    },
    {
      "year": 1969,
      "round": 2,
      "pick": 51,
      "name": "Tommy Maxwell",
      "position": "DB",
      "nflTeam": "Baltimore Colts"
    },
    {
      "year": 1969,
      "round": 8,
      "pick": 184,
      "name": "Bill Hobbs",
      "position": "LB",
      "nflTeam": "Philadelphia Eagles"
    },
    {
      "year": 1969,
      "round": 12,
      "pick": 298,
      "name": "Tom Buckman",
      "position": "TE",
      "nflTeam": "Green Bay Packers"
    },
    {
      "year": 1969,
      "round": 13,
      "pick": 338,
      "name": "Steve O'Neal",
      "position": "P",
      "nflTeam": "New York Jets"
    },
    {
      "year": 1969,
      "round": 16,
      "pick": 397,
      "name": "Edd Hargett",
      "position": "QB",
      "nflTeam": "New Orleans Saints"
    },
    {
      "year": 1968,
      "round": 1,
      "pick": 19,
      "name": "Mo Moorman",
      "position": "G",
      "nflTeam": "Kansas City Chiefs"
    },
    {
      "year": 1967,
      "round": 11,
      "pick": 266,
      "name": "Jack Pyburn",
      "position": "T",
      "nflTeam": "Miami Dolphins"
    },
    {
      "year": 1967,
      "round": 15,
      "pick": 378,
      "name": "Ed Breding",
      "position": "LB",
      "nflTeam": "Washington Redskins"
    }
  ]
}