{
  "source": "espn",
  "year": 2000,
  "scrapedAt": "2026-03-27T20:04:14.823Z",
  "count": 14,
  "recruits": [
    {
      "rank": 1,
      "name": "Marcus Bowers",
      "firstName": "Marcus",
      "lastName": "Bowers",
      "espnId": "192946",
      "position": "ILB",
      "positionName": null,
      "city": "Detroit",
      "state": "MI",
      "stateFull": "Michigan",
      "height": "6-0",
      "heightInches": 72,
      "weight": 213,
      "highSchool": "Finney High School",
      "highSchoolCity": "Detroit",
      "highSchoolState": "Michigan",
      "classYear": 2000,
      "grade": 40,
      "status": {
        "id": 0,
        "description": "Undeclared"
      },
      "attributes": {
        "40 YD": 5.22,
        "3 CD": 99,
        "20 YS": 4.59,
        "VJ": 22.9
      },
      "committedSchool": null,
      "schools": null,
      "schoolInterests": 0,
      "source": "espn"
    },
    {
      "rank": 2,
      "name": "Draven Coley",
      "firstName": "Draven",
      "lastName": "Coley",
      "espnId": "210125",
      "position": "WR",
      "positionName": null,
      "city": "Jackson",
      "state": "TN",
      "stateFull": "Tennessee",
      "height": "6-4",
      "heightInches": 76,
      "weight": 190,
      "highSchool": "Liberty Tech High School",
      "highSchoolCity": "Jackson",
      "highSchoolState": "Tennessee",
      "classYear": 2000,
      "grade": 40,
      "status": {
        "id": 0,
        "description": "Undeclared"
      },
      "attributes": {
        "40 YD": 4.78,
        "3 CD": 99,
        "20 YS": 4.6,
        "VJ": 33.2
      },
      "committedSchool": null,
      "schools": null,
      "schoolInterests": 0,
      "source": "espn"
    },
    {
      "rank": 3,
      "name": "Derek Dressler",
      "firstName": "Derek",
      "lastName": "Dressler",
      "espnId": "193647",
      "position": "OG",
      "positionName": null,
      "city": "Covington",
      "state": "VA",
      "stateFull": "Virginia",
      "height": "6-1",
      "heightInches": 73,
      "weight": 308,
      "highSchool": "Covington High School",
      "highSchoolCity": "Covington",
      "highSchoolState": "Virginia",
      "classYear": 2000,
      "grade": 40,
      "status": {
        "id": 0,
        "description": "Undeclared"
      },
      "attributes": {
        "40 YD": 5.63,
        "3 CD": 99,
        "20 YS": 4.84,
        "VJ": 21.7
      },
      "committedSchool": null,
      "schools": null,
      "schoolInterests": 0,
      "source": "espn"
    },
    {
      "rank": 4,
      "name": "Blayne Fortune",
      "firstName": "Blayne",
      "lastName": "Fortune",
      "espnId": "192919",
      "position": "WR",
      "positionName": null,
      "city": "Davison",
      "state": "MI",
      "stateFull": "Michigan",
      "height": "6-1",
      "heightInches": 73,
      "weight": 171,
      "highSchool": "Davison High School",
      "highSchoolCity": "Davison",
      "highSchoolState": "Michigan",
      "classYear": 2000,
      "grade": 40,
      "status": {
        "id": 0,
        "description": "Undeclared"
      },
      "attributes": {
        "40 YD": 5.1,
        "3 CD": 99,
        "20 YS": 4.56,
        "VJ": 30.3
      },
      "committedSchool": null,
      "schools": null,
      "schoolInterests": 0,
      "source": "espn"
    },
    {
      "rank": 5,
      "name": "Devon Hathaway",
      "firstName": "Devon",
      "lastName": "Hathaway",
      "espnId": "194818",
      "position": "S",
      "positionName": null,
      "city": "Santee",
      "state": "CA",
      "stateFull": "California",
      "height": "5-9",
      "heightInches": 69,
      "weight": 166,
      "highSchool": "West Hills High School",
      "highSchoolCity": "Santee",
      "highSchoolState": "California",
      "classYear": 2000,
      "grade": 40,
      "status": {
        "id": 0,
        "description": "Undeclared"
      },
      "attributes": {
        "40 YD": 4.96,
        "3 CD": 99,
        "20 YS": 4.72,
        "VJ": 36.3
      },
      "committedSchool": null,
      "schools": null,
      "schoolInterests": 0,
      "source": "espn"
    },
    {
      "rank": 6,
      "name": "Jarrod Kelley",
      "firstName": "Jarrod",
      "lastName": "Kelley",
      "espnId": "199438",
      "position": "CB",
      "positionName": null,
      "city": "Winter Haven",
      "state": "FL",
      "stateFull": "Florida",
      "height": "5-9",
      "heightInches": 69,
      "weight": 146,
      "highSchool": "Winter Haven High School",
      "highSchoolCity": "Winter Haven",
      "highSchoolState": "Florida",
      "classYear": 2000,
      "grade": 40,
      "status": {
        "id": 0,
        "description": "Undeclared"
      },
      "attributes": {
        "40 YD": 99,
        "3 CD": 99,
        "20 YS": 4.65,
        "VJ": 32.5
      },
      "committedSchool": null,
      "schools": null,
      "schoolInterests": 0,
      "source": "espn"
    },
    {
      "rank": 7,
      "name": "Kordell Lacy",
      "firstName": "Kordell",
      "lastName": "Lacy",
      "espnId": "194814",
      "position": "RB",
      "positionName": null,
      "city": "Brentwood",
      "state": "CA",
      "stateFull": "California",
      "height": "5-7",
      "heightInches": 67,
      "weight": 168,
      "highSchool": "Heritage High School",
      "highSchoolCity": "Brentwood",
      "highSchoolState": "California",
      "classYear": 2000,
      "grade": 40,
      "status": {
        "id": 0,
        "description": "Undeclared"
      },
      "attributes": {
        "40 YD": 4.71,
        "3 CD": 99,
        "20 YS": 4.56,
        "VJ": 30.6
      },
      "committedSchool": null,
      "schools": null,
      "schoolInterests": 0,
      "source": "espn"
    },
    {
      "rank": 8,
      "name": "Jake Leone",
      "firstName": "Jake",
      "lastName": "Leone",
      "espnId": "227792",
      "position": "TE-H",
      "positionName": null,
      "city": "Fort Collins",
      "state": "CO",
      "stateFull": "Colorado",
      "height": "6-3",
      "heightInches": 75,
      "weight": 197,
      "highSchool": "Fort Collins High School",
      "highSchoolCity": "Fort Collins",
      "highSchoolState": "Colorado",
      "classYear": 2000,
      "grade": 40,
      "status": {
        "id": 0,
        "description": "Undeclared"
      },
      "attributes": {
        "40 YD": 99,
        "3 CD": 99,
        "20 YS": 99
      },
      "committedSchool": null,
      "schools": null,
      "schoolInterests": 0,
      "source": "espn"
    },
    {
      "rank": 9,
      "name": "Justin Okeefe",
      "firstName": "Justin",
      "lastName": "Okeefe",
      "espnId": "194824",
      "position": "WR",
      "positionName": null,
      "city": "Los Angeles",
      "state": "CA",
      "stateFull": "California",
      "height": "6-1",
      "heightInches": 73,
      "weight": 175,
      "highSchool": "Crenshaw High School",
      "highSchoolCity": "Los Angeles",
      "highSchoolState": "California",
      "classYear": 2000,
      "grade": 40,
      "status": {
        "id": 0,
        "description": "Undeclared"
      },
      "attributes": {
        "40 YD": 4.89,
        "3 CD": 99,
        "20 YS": 4.53,
        "VJ": 32.4
      },
      "committedSchool": null,
      "schools": null,
      "schoolInterests": 0,
      "source": "espn"
    },
    {
      "rank": 10,
      "name": "Lewis Robinson",
      "firstName": "Lewis",
      "lastName": "Robinson",
      "espnId": "53268",
      "position": "FB",
      "positionName": null,
      "city": "Richmond",
      "state": "CA",
      "stateFull": "California",
      "height": "5-8",
      "heightInches": 68,
      "weight": 230,
      "highSchool": "De Anza High School",
      "highSchoolCity": "Richmond",
      "highSchoolState": "California",
      "classYear": 2000,
      "grade": 45,
      "status": {
        "id": 0,
        "description": "Undeclared"
      },
      "attributes": {
        "RK": 1,
        "POS RK": 1
      },
      "committedSchool": null,
      "schools": null,
      "schoolInterests": 0,
      "source": "espn"
    },
    {
      "rank": 11,
      "name": "Brian Scott",
      "firstName": "Brian",
      "lastName": "Scott",
      "espnId": "194794",
      "position": "RB",
      "positionName": null,
      "city": "Dana Point",
      "state": "CA",
      "stateFull": "California",
      "height": "5-11",
      "heightInches": 71,
      "weight": 172,
      "highSchool": "Dana Hills High School",
      "highSchoolCity": "Dana Point",
      "highSchoolState": "California",
      "classYear": 2000,
      "grade": 40,
      "status": {
        "id": 0,
        "description": "Undeclared"
      },
      "attributes": {
        "40 YD": 4.91,
        "3 CD": 99,
        "20 YS": 4.31,
        "VJ": 32.6
      },
      "committedSchool": null,
      "schools": null,
      "schoolInterests": 0,
      "source": "espn"
    },
    {
      "rank": 12,
      "name": "Quinntin Teeling",
      "firstName": "Quinntin",
      "lastName": "Teeling",
      "espnId": "192818",
      "position": "CB",
      "positionName": null,
      "city": "Tallmadge",
      "state": "OH",
      "stateFull": "Ohio",
      "height": "5-10",
      "heightInches": 70,
      "weight": 156,
      "highSchool": "Tallmadge High School",
      "highSchoolCity": "Tallmadge",
      "highSchoolState": "Ohio",
      "classYear": 2000,
      "grade": 40,
      "status": {
        "id": 0,
        "description": "Undeclared"
      },
      "attributes": {
        "40 YD": 4.8,
        "3 CD": 99,
        "20 YS": 4.47,
        "VJ": 30.6
      },
      "committedSchool": null,
      "schools": null,
      "schoolInterests": 0,
      "source": "espn"
    },
    {
      "rank": 13,
      "name": "Ronnie Thornton",
      "firstName": "Ronnie",
      "lastName": "Thornton",
      "espnId": "52828",
      "position": "ILB",
      "positionName": null,
      "city": "Miami",
      "state": "FL",
      "stateFull": "Florida",
      "height": null,
      "heightInches": null,
      "weight": null,
      "highSchool": "Miami Killian High School",
      "highSchoolCity": "Miami",
      "highSchoolState": "Florida",
      "classYear": 2000,
      "grade": 45,
      "status": {
        "id": 0,
        "description": "Undeclared"
      },
      "attributes": {
        "RK": 1,
        "POS RK": 1
      },
      "committedSchool": null,
      "schools": null,
      "schoolInterests": 0,
      "source": "espn"
    },
    {
      "rank": 14,
      "name": "Titus Williams",
      "firstName": "Titus",
      "lastName": "Williams",
      "espnId": "192979",
      "position": "WR",
      "positionName": null,
      "city": "New Albany",
      "state": "OH",
      "stateFull": "Ohio",
      "height": "5-11",
      "heightInches": 71,
      "weight": 157,
      "highSchool": "New Albany High School",
      "highSchoolCity": "New Albany",
      "highSchoolState": "Ohio",
      "classYear": 2000,
      "grade": 40,
      "status": {
        "id": 0,
        "description": "Undeclared"
      },
      "attributes": {
        "40 YD": 4.85,
        "3 CD": 99,
        "20 YS": 4.61,
        "VJ": 29
      },
      "committedSchool": null,
      "schools": null,
      "schoolInterests": 0,
      "source": "espn"
    }
  ]
}