[
  {
    "year": 2014,
    "team": "Navy",
    "conference": "FBS Independents",
    "fpi": 0.593,
    "resumeRanks": {
      "strengthOfRecord": 68,
      "fpi": 69,
      "averageWinProbability": 41,
      "strengthOfSchedule": 81,
      "remainingStrengthOfSchedule": null,
      "gameControl": 65
    },
    "efficiencies": {
      "overall": 48.095,
      "offense": 61.471,
      "defense": 37.89,
      "specialTeams": 43.343
    }
  },
  {
    "year": 2014,
    "team": "UAB",
    "conference": "Conference USA",
    "fpi": -6.056,
    "resumeRanks": {
      "strengthOfRecord": 80,
      "fpi": 90,
      "averageWinProbability": 72,
      "strengthOfSchedule": 90,
      "remainingStrengthOfSchedule": null,
      "gameControl": 80
    },
    "efficiencies": {
      "overall": 38.454,
      "offense": 33.38,
      "defense": 42.666,
      "specialTeams": 66.77
    }
  },
  {
    "year": 2014,
    "team": "Massachusetts",
    "conference": "Mid-American",
    "fpi": -14.742,
    "resumeRanks": {
      "strengthOfRecord": 120,
      "fpi": 118,
      "averageWinProbability": 82,
      "strengthOfSchedule": 118,
      "remainingStrengthOfSchedule": null,
      "gameControl": 105
    },
    "efficiencies": {
      "overall": 26.589,
      "offense": 38.643,
      "defense": 25.334,
      "specialTeams": 45.218
    }
  },
  {
    "year": 2014,
    "team": "UCF",
    "conference": "American Athletic",
    "fpi": 4.669,
    "resumeRanks": {
      "strengthOfRecord": 50,
      "fpi": 55,
      "averageWinProbability": 32,
      "strengthOfSchedule": 87,
      "remainingStrengthOfSchedule": null,
      "gameControl": 56
    },
    "efficiencies": {
      "overall": 54.457,
      "offense": 43.841,
      "defense": 66.929,
      "specialTeams": 38.18
    }
  },
  {
    "year": 2014,
    "team": "Cincinnati",
    "conference": "American Athletic",
    "fpi": 6.282,
    "resumeRanks": {
      "strengthOfRecord": 43,
      "fpi": 50,
      "averageWinProbability": 35,
      "strengthOfSchedule": 71,
      "remainingStrengthOfSchedule": null,
      "gameControl": 49
    },
    "efficiencies": {
      "overall": 58.779,
      "offense": 67.073,
      "defense": 44.279,
      "specialTeams": 57.934
    }
  },
  {
    "year": 2014,
    "team": "Houston",
    "conference": "American Athletic",
    "fpi": 4.94,
    "resumeRanks": {
      "strengthOfRecord": 71,
      "fpi": 54,
      "averageWinProbability": 64,
      "strengthOfSchedule": 100,
      "remainingStrengthOfSchedule": null,
      "gameControl": 86
    },
    "efficiencies": {
      "overall": 45.119,
      "offense": 42.495,
      "defense": 50.432,
      "specialTeams": 48.06
    }
  },
  {
    "year": 2014,
    "team": "SMU",
    "conference": "American Athletic",
    "fpi": -20.52,
    "resumeRanks": {
      "strengthOfRecord": 118,
      "fpi": 125,
      "averageWinProbability": 128,
      "strengthOfSchedule": 60,
      "remainingStrengthOfSchedule": null,
      "gameControl": 117
    },
    "efficiencies": {
      "overall": 10.246,
      "offense": 10.186,
      "defense": 22.247,
      "specialTeams": 44.29
    }
  },
  {
    "year": 2014,
    "team": "UConn",
    "conference": "American Athletic",
    "fpi": -14.844,
    "resumeRanks": {
      "strengthOfRecord": 122,
      "fpi": 119,
      "averageWinProbability": 123,
      "strengthOfSchedule": 84,
      "remainingStrengthOfSchedule": null,
      "gameControl": 117
    },
    "efficiencies": {
      "overall": 20.57,
      "offense": 10.389,
      "defense": 42.083,
      "specialTeams": 51.431
    }
  },
  {
    "year": 2014,
    "team": "South Florida",
    "conference": "American Athletic",
    "fpi": -10.132,
    "resumeRanks": {
      "strengthOfRecord": 101,
      "fpi": 102,
      "averageWinProbability": 114,
      "strengthOfSchedule": 70,
      "remainingStrengthOfSchedule": null,
      "gameControl": 111
    },
    "efficiencies": {
      "overall": 25.087,
      "offense": 23.08,
      "defense": 35.641,
      "specialTeams": 50.531
    }
  },
  {
    "year": 2014,
    "team": "Memphis",
    "conference": "American Athletic",
    "fpi": 7.906,
    "resumeRanks": {
      "strengthOfRecord": 29,
      "fpi": 40,
      "averageWinProbability": 14,
      "strengthOfSchedule": 82,
      "remainingStrengthOfSchedule": null,
      "gameControl": 31
    },
    "efficiencies": {
      "overall": 65.03,
      "offense": 45.689,
      "defense": 68.665,
      "specialTeams": 76.368
    }
  },
  {
    "year": 2014,
    "team": "Temple",
    "conference": "American Athletic",
    "fpi": -1.377,
    "resumeRanks": {
      "strengthOfRecord": 78,
      "fpi": 76,
      "averageWinProbability": 67,
      "strengthOfSchedule": 80,
      "remainingStrengthOfSchedule": null,
      "gameControl": 81
    },
    "efficiencies": {
      "overall": 47.076,
      "offense": 18.748,
      "defense": 70.388,
      "specialTeams": 61.873
    }
  },
  {
    "year": 2014,
    "team": "East Carolina",
    "conference": "American Athletic",
    "fpi": 3.828,
    "resumeRanks": {
      "strengthOfRecord": 62,
      "fpi": 59,
      "averageWinProbability": 52,
      "strengthOfSchedule": 76,
      "remainingStrengthOfSchedule": null,
      "gameControl": 64
    },
    "efficiencies": {
      "overall": 56.627,
      "offense": 64.06,
      "defense": 49.395,
      "specialTeams": 36.18
    }
  },
  {
    "year": 2014,
    "team": "Tulane",
    "conference": "American Athletic",
    "fpi": -9.698,
    "resumeRanks": {
      "strengthOfRecord": 103,
      "fpi": 100,
      "averageWinProbability": 103,
      "strengthOfSchedule": 65,
      "remainingStrengthOfSchedule": null,
      "gameControl": 90
    },
    "efficiencies": {
      "overall": 31.328,
      "offense": 23.636,
      "defense": 57.524,
      "specialTeams": 23.665
    }
  },
  {
    "year": 2014,
    "team": "Tulsa",
    "conference": "American Athletic",
    "fpi": -12.969,
    "resumeRanks": {
      "strengthOfRecord": 117,
      "fpi": 115,
      "averageWinProbability": 122,
      "strengthOfSchedule": 69,
      "remainingStrengthOfSchedule": null,
      "gameControl": 116
    },
    "efficiencies": {
      "overall": 22.871,
      "offense": 37.717,
      "defense": 15.153,
      "specialTeams": 60.895
    }
  },
  {
    "year": 2014,
    "team": "New Mexico State",
    "conference": "Sun Belt",
    "fpi": -21.765,
    "resumeRanks": {
      "strengthOfRecord": 126,
      "fpi": 126,
      "averageWinProbability": 124,
      "strengthOfSchedule": 124,
      "remainingStrengthOfSchedule": null,
      "gameControl": 117
    },
    "efficiencies": {
      "overall": 13.101,
      "offense": 22.127,
      "defense": 21.023,
      "specialTeams": 23.138
    }
  },
  {
    "year": 2014,
    "team": "Idaho",
    "conference": "Sun Belt",
    "fpi": -19.271,
    "resumeRanks": {
      "strengthOfRecord": 128,
      "fpi": 123,
      "averageWinProbability": 126,
      "strengthOfSchedule": 121,
      "remainingStrengthOfSchedule": null,
      "gameControl": 117
    },
    "efficiencies": {
      "overall": 15.089,
      "offense": 27.189,
      "defense": 11.36,
      "specialTeams": 62.968
    }
  },
  {
    "year": 2014,
    "team": "Notre Dame",
    "conference": "FBS Independents",
    "fpi": 12.55,
    "resumeRanks": {
      "strengthOfRecord": 33,
      "fpi": 50,
      "averageWinProbability": 45,
      "strengthOfSchedule": 29,
      "remainingStrengthOfSchedule": null,
      "gameControl": 32
    },
    "efficiencies": {
      "overall": 64.14,
      "offense": 72.391,
      "defense": 50.306,
      "specialTeams": 46.193
    }
  },
  {
    "year": 2014,
    "team": "Georgia",
    "conference": "SEC",
    "fpi": 24.267,
    "resumeRanks": {
      "strengthOfRecord": 11,
      "fpi": 5,
      "averageWinProbability": 6,
      "strengthOfSchedule": 20,
      "remainingStrengthOfSchedule": null,
      "gameControl": 6
    },
    "efficiencies": {
      "overall": 86.277,
      "offense": 87.832,
      "defense": 69.989,
      "specialTeams": 61.443
    }
  },
  {
    "year": 2014,
    "team": "Florida",
    "conference": "SEC",
    "fpi": 15.671,
    "resumeRanks": {
      "strengthOfRecord": 31,
      "fpi": 22,
      "averageWinProbability": 43,
      "strengthOfSchedule": 33,
      "remainingStrengthOfSchedule": null,
      "gameControl": 23
    },
    "efficiencies": {
      "overall": 70.146,
      "offense": 35.309,
      "defense": 85.654,
      "specialTeams": 60.04
    }
  },
  {
    "year": 2014,
    "team": "Tennessee",
    "conference": "SEC",
    "fpi": 12.329,
    "resumeRanks": {
      "strengthOfRecord": 37,
      "fpi": 31,
      "averageWinProbability": 49,
      "strengthOfSchedule": 18,
      "remainingStrengthOfSchedule": null,
      "gameControl": 24
    },
    "efficiencies": {
      "overall": 67.444,
      "offense": 56.134,
      "defense": 67.129,
      "specialTeams": 66.142
    }
  },
  {
    "year": 2014,
    "team": "South Carolina",
    "conference": "SEC",
    "fpi": 11.433,
    "resumeRanks": {
      "strengthOfRecord": 41,
      "fpi": 33,
      "averageWinProbability": 50,
      "strengthOfSchedule": 28,
      "remainingStrengthOfSchedule": null,
      "gameControl": 33
    },
    "efficiencies": {
      "overall": 62.34,
      "offense": 75.525,
      "defense": 37.52,
      "specialTeams": 62.554
    }
  },
  {
    "year": 2014,
    "team": "Kentucky",
    "conference": "SEC",
    "fpi": 3.258,
    "resumeRanks": {
      "strengthOfRecord": 59,
      "fpi": 60,
      "averageWinProbability": 89,
      "strengthOfSchedule": 36,
      "remainingStrengthOfSchedule": null,
      "gameControl": 55
    },
    "efficiencies": {
      "overall": 54.532,
      "offense": 57.668,
      "defense": 50.161,
      "specialTeams": 49.017
    }
  },
  {
    "year": 2014,
    "team": "Vanderbilt",
    "conference": "SEC",
    "fpi": -8.228,
    "resumeRanks": {
      "strengthOfRecord": 93,
      "fpi": 94,
      "averageWinProbability": 120,
      "strengthOfSchedule": 41,
      "remainingStrengthOfSchedule": null,
      "gameControl": 93
    },
    "efficiencies": {
      "overall": 24.365,
      "offense": 19.562,
      "defense": 39.376,
      "specialTeams": 45.461
    }
  },
  {
    "year": 2014,
    "team": "Oklahoma State",
    "conference": "Big 12",
    "fpi": 6.457,
    "resumeRanks": {
      "strengthOfRecord": 38,
      "fpi": 48,
      "averageWinProbability": 88,
      "strengthOfSchedule": 38,
      "remainingStrengthOfSchedule": null,
      "gameControl": 58
    },
    "efficiencies": {
      "overall": 56.109,
      "offense": 50.574,
      "defense": 52.698,
      "specialTeams": 68.071
    }
  },
  {
    "year": 2014,
    "team": "Kansas State",
    "conference": "Big 12",
    "fpi": 17.279,
    "resumeRanks": {
      "strengthOfRecord": 19,
      "fpi": 18,
      "averageWinProbability": 28,
      "strengthOfSchedule": 39,
      "remainingStrengthOfSchedule": null,
      "gameControl": 18
    },
    "efficiencies": {
      "overall": 77.252,
      "offense": 75.015,
      "defense": 65.245,
      "specialTeams": 67.006
    }
  },
  {
    "year": 2014,
    "team": "Baylor",
    "conference": "Big 12",
    "fpi": 23.891,
    "resumeRanks": {
      "strengthOfRecord": 7,
      "fpi": 6,
      "averageWinProbability": 2,
      "strengthOfSchedule": 54,
      "remainingStrengthOfSchedule": null,
      "gameControl": 4
    },
    "efficiencies": {
      "overall": 86.246,
      "offense": 87.713,
      "defense": 70.591,
      "specialTeams": 52.71
    }
  },
  {
    "year": 2014,
    "team": "Iowa State",
    "conference": "Big 12",
    "fpi": -3.897,
    "resumeRanks": {
      "strengthOfRecord": 95,
      "fpi": 85,
      "averageWinProbability": 118,
      "strengthOfSchedule": 6,
      "remainingStrengthOfSchedule": null,
      "gameControl": 84
    },
    "efficiencies": {
      "overall": 38.564,
      "offense": 51.142,
      "defense": 32.105,
      "specialTeams": 47.685
    }
  },
  {
    "year": 2014,
    "team": "Texas Tech",
    "conference": "Big 12",
    "fpi": 2.113,
    "resumeRanks": {
      "strengthOfRecord": 73,
      "fpi": 64,
      "averageWinProbability": 93,
      "strengthOfSchedule": 27,
      "remainingStrengthOfSchedule": null,
      "gameControl": 62
    },
    "efficiencies": {
      "overall": 47.204,
      "offense": 68.362,
      "defense": 31.307,
      "specialTeams": 39.596
    }
  },
  {
    "year": 2014,
    "team": "Kansas",
    "conference": "Big 12",
    "fpi": -6.517,
    "resumeRanks": {
      "strengthOfRecord": 81,
      "fpi": 91,
      "averageWinProbability": 113,
      "strengthOfSchedule": 19,
      "remainingStrengthOfSchedule": null,
      "gameControl": 74
    },
    "efficiencies": {
      "overall": 36.359,
      "offense": 31.073,
      "defense": 52.901,
      "specialTeams": 34.193
    }
  },
  {
    "year": 2014,
    "team": "TCU",
    "conference": "Big 12",
    "fpi": 26.11,
    "resumeRanks": {
      "strengthOfRecord": 4,
      "fpi": 3,
      "averageWinProbability": 1,
      "strengthOfSchedule": 45,
      "remainingStrengthOfSchedule": null,
      "gameControl": 2
    },
    "efficiencies": {
      "overall": 88.026,
      "offense": 75.762,
      "defense": 88.001,
      "specialTeams": 57.664
    }
  },
  {
    "year": 2014,
    "team": "West Virginia",
    "conference": "Big 12",
    "fpi": 12.138,
    "resumeRanks": {
      "strengthOfRecord": 35,
      "fpi": 32,
      "averageWinProbability": 63,
      "strengthOfSchedule": 9,
      "remainingStrengthOfSchedule": null,
      "gameControl": 36
    },
    "efficiencies": {
      "overall": 67.039,
      "offense": 60.158,
      "defense": 70.475,
      "specialTeams": 43.628
    }
  },
  {
    "year": 2014,
    "team": "UTEP",
    "conference": "Conference USA",
    "fpi": -9.189,
    "resumeRanks": {
      "strengthOfRecord": 82,
      "fpi": 97,
      "averageWinProbability": 58,
      "strengthOfSchedule": 102,
      "remainingStrengthOfSchedule": null,
      "gameControl": 79
    },
    "efficiencies": {
      "overall": 36.066,
      "offense": 32.58,
      "defense": 43.872,
      "specialTeams": 54.713
    }
  },
  {
    "year": 2014,
    "team": "Rice",
    "conference": "Conference USA",
    "fpi": -3.211,
    "resumeRanks": {
      "strengthOfRecord": 67,
      "fpi": 84,
      "averageWinProbability": 69,
      "strengthOfSchedule": 89,
      "remainingStrengthOfSchedule": null,
      "gameControl": 72
    },
    "efficiencies": {
      "overall": 43.274,
      "offense": 49.573,
      "defense": 40.577,
      "specialTeams": 46.664
    }
  },
  {
    "year": 2014,
    "team": "Oregon",
    "conference": "Pac-12",
    "fpi": 28.344,
    "resumeRanks": {
      "strengthOfRecord": 5,
      "fpi": 1,
      "averageWinProbability": 4,
      "strengthOfSchedule": 13,
      "remainingStrengthOfSchedule": null,
      "gameControl": 1
    },
    "efficiencies": {
      "overall": 88.741,
      "offense": 91.296,
      "defense": 69.883,
      "specialTeams": 58.151
    }
  },
  {
    "year": 2014,
    "team": "Stanford",
    "conference": "Pac-12",
    "fpi": 19.186,
    "resumeRanks": {
      "strengthOfRecord": 25,
      "fpi": 12,
      "averageWinProbability": 19,
      "strengthOfSchedule": 23,
      "remainingStrengthOfSchedule": null,
      "gameControl": 11
    },
    "efficiencies": {
      "overall": 79.368,
      "offense": 62.596,
      "defense": 84.001,
      "specialTeams": 50.042
    }
  },
  {
    "year": 2014,
    "team": "Washington",
    "conference": "Pac-12",
    "fpi": 11.308,
    "resumeRanks": {
      "strengthOfRecord": 45,
      "fpi": 34,
      "averageWinProbability": 57,
      "strengthOfSchedule": 48,
      "remainingStrengthOfSchedule": null,
      "gameControl": 47
    },
    "efficiencies": {
      "overall": 64.283,
      "offense": 47.565,
      "defense": 70.973,
      "specialTeams": 58.322
    }
  },
  {
    "year": 2014,
    "team": "California",
    "conference": "Pac-12",
    "fpi": 6.509,
    "resumeRanks": {
      "strengthOfRecord": 54,
      "fpi": 47,
      "averageWinProbability": 87,
      "strengthOfSchedule": 10,
      "remainingStrengthOfSchedule": null,
      "gameControl": 52
    },
    "efficiencies": {
      "overall": 57.082,
      "offense": 73.94,
      "defense": 36.237,
      "specialTeams": 49.875
    }
  },
  {
    "year": 2014,
    "team": "Oregon State",
    "conference": "Pac-12",
    "fpi": 3.205,
    "resumeRanks": {
      "strengthOfRecord": 65,
      "fpi": 61,
      "averageWinProbability": 90,
      "strengthOfSchedule": 37,
      "remainingStrengthOfSchedule": null,
      "gameControl": 63
    },
    "efficiencies": {
      "overall": 47.507,
      "offense": 49.597,
      "defense": 46.957,
      "specialTeams": 48.348
    }
  },
  {
    "year": 2014,
    "team": "Washington State",
    "conference": "Pac-12",
    "fpi": 2.771,
    "resumeRanks": {
      "strengthOfRecord": 79,
      "fpi": 62,
      "averageWinProbability": 106,
      "strengthOfSchedule": 12,
      "remainingStrengthOfSchedule": null,
      "gameControl": 71
    },
    "efficiencies": {
      "overall": 44.461,
      "offense": 61.08,
      "defense": 38.792,
      "specialTeams": 20.618
    }
  },
  {
    "year": 2014,
    "team": "USC",
    "conference": "Pac-12",
    "fpi": 19.155,
    "resumeRanks": {
      "strengthOfRecord": 22,
      "fpi": 13,
      "averageWinProbability": 12,
      "strengthOfSchedule": 8,
      "remainingStrengthOfSchedule": null,
      "gameControl": 9
    },
    "efficiencies": {
      "overall": 78.729,
      "offense": 74.596,
      "defense": 70.508,
      "specialTeams": 60.969
    }
  },
  {
    "year": 2014,
    "team": "BYU",
    "conference": "FBS Independents",
    "fpi": 7.53,
    "resumeRanks": {
      "strengthOfRecord": 53,
      "fpi": 43,
      "averageWinProbability": 31,
      "strengthOfSchedule": 67,
      "remainingStrengthOfSchedule": null,
      "gameControl": 43
    },
    "efficiencies": {
      "overall": 57.42,
      "offense": 58.521,
      "defense": 51.207,
      "specialTeams": 56.89
    }
  },
  {
    "year": 2014,
    "team": "Auburn",
    "conference": "SEC",
    "fpi": 21.898,
    "resumeRanks": {
      "strengthOfRecord": 17,
      "fpi": 8,
      "averageWinProbability": 47,
      "strengthOfSchedule": 2,
      "remainingStrengthOfSchedule": null,
      "gameControl": 15
    },
    "efficiencies": {
      "overall": 77.734,
      "offense": 86.172,
      "defense": 58.363,
      "specialTeams": 41.655
    }
  },
  {
    "year": 2014,
    "team": "LSU",
    "conference": "SEC",
    "fpi": 18.998,
    "resumeRanks": {
      "strengthOfRecord": 21,
      "fpi": 15,
      "averageWinProbability": 61,
      "strengthOfSchedule": 7,
      "remainingStrengthOfSchedule": null,
      "gameControl": 28
    },
    "efficiencies": {
      "overall": 72.909,
      "offense": 60.527,
      "defense": 76.621,
      "specialTeams": 51.753
    }
  },
  {
    "year": 2014,
    "team": "Miami (OH)",
    "conference": "Mid-American",
    "fpi": -15.917,
    "resumeRanks": {
      "strengthOfRecord": 125,
      "fpi": 121,
      "averageWinProbability": 117,
      "strengthOfSchedule": 97,
      "remainingStrengthOfSchedule": null,
      "gameControl": 117
    },
    "efficiencies": {
      "overall": 21.198,
      "offense": 26.879,
      "defense": 28.721,
      "specialTeams": 36.626
    }
  },
  {
    "year": 2014,
    "team": "Ohio",
    "conference": "Mid-American",
    "fpi": -10.82,
    "resumeRanks": {
      "strengthOfRecord": 96,
      "fpi": 106,
      "averageWinProbability": 95,
      "strengthOfSchedule": 114,
      "remainingStrengthOfSchedule": null,
      "gameControl": 112
    },
    "efficiencies": {
      "overall": 26.451,
      "offense": 24.142,
      "defense": 39.736,
      "specialTeams": 43.703
    }
  },
  {
    "year": 2014,
    "team": "Kent State",
    "conference": "Mid-American",
    "fpi": -14.665,
    "resumeRanks": {
      "strengthOfRecord": 121,
      "fpi": 117,
      "averageWinProbability": 121,
      "strengthOfSchedule": 103,
      "remainingStrengthOfSchedule": null,
      "gameControl": 117
    },
    "efficiencies": {
      "overall": 22.011,
      "offense": 23.132,
      "defense": 31.915,
      "specialTeams": 42.983
    }
  },
  {
    "year": 2014,
    "team": "Akron",
    "conference": "Mid-American",
    "fpi": -10.663,
    "resumeRanks": {
      "strengthOfRecord": 107,
      "fpi": 105,
      "averageWinProbability": 76,
      "strengthOfSchedule": 120,
      "remainingStrengthOfSchedule": null,
      "gameControl": 101
    },
    "efficiencies": {
      "overall": 30.382,
      "offense": 20.728,
      "defense": 46.932,
      "specialTeams": 57.423
    }
  },
  {
    "year": 2014,
    "team": "Toledo",
    "conference": "Mid-American",
    "fpi": 1.083,
    "resumeRanks": {
      "strengthOfRecord": 60,
      "fpi": 68,
      "averageWinProbability": 51,
      "strengthOfSchedule": 101,
      "remainingStrengthOfSchedule": null,
      "gameControl": 78
    },
    "efficiencies": {
      "overall": 47.293,
      "offense": 60.164,
      "defense": 35.02,
      "specialTeams": 49.356
    }
  },
  {
    "year": 2014,
    "team": "UCLA",
    "conference": "Pac-12",
    "fpi": 19.205,
    "resumeRanks": {
      "strengthOfRecord": 8,
      "fpi": 11,
      "averageWinProbability": 29,
      "strengthOfSchedule": 1,
      "remainingStrengthOfSchedule": null,
      "gameControl": 14
    },
    "efficiencies": {
      "overall": 73.756,
      "offense": 75.166,
      "defense": 64.433,
      "specialTeams": 48.689
    }
  },
  {
    "year": 2014,
    "team": "Utah",
    "conference": "Pac-12",
    "fpi": 13.507,
    "resumeRanks": {
      "strengthOfRecord": 20,
      "fpi": 27,
      "averageWinProbability": 44,
      "strengthOfSchedule": 17,
      "remainingStrengthOfSchedule": null,
      "gameControl": 22
    },
    "efficiencies": {
      "overall": 73.565,
      "offense": 49.524,
      "defense": 77.743,
      "specialTeams": 76.633
    }
  },
  {
    "year": 2014,
    "team": "Arizona State",
    "conference": "Pac-12",
    "fpi": 14.153,
    "resumeRanks": {
      "strengthOfRecord": 14,
      "fpi": 24,
      "averageWinProbability": 22,
      "strengthOfSchedule": 26,
      "remainingStrengthOfSchedule": null,
      "gameControl": 17
    },
    "efficiencies": {
      "overall": 73.829,
      "offense": 63.902,
      "defense": 74.701,
      "specialTeams": 52.447
    }
  },
  {
    "year": 2014,
    "team": "Arizona",
    "conference": "Pac-12",
    "fpi": 14.145,
    "resumeRanks": {
      "strengthOfRecord": 15,
      "fpi": 25,
      "averageWinProbability": 60,
      "strengthOfSchedule": 22,
      "remainingStrengthOfSchedule": null,
      "gameControl": 37
    },
    "efficiencies": {
      "overall": 66.915,
      "offense": 62.999,
      "defense": 66.049,
      "specialTeams": 45.41
    }
  },
  {
    "year": 2014,
    "team": "Colorado",
    "conference": "Pac-12",
    "fpi": -1.022,
    "resumeRanks": {
      "strengthOfRecord": 99,
      "fpi": 75,
      "averageWinProbability": 104,
      "strengthOfSchedule": 14,
      "remainingStrengthOfSchedule": null,
      "gameControl": 70
    },
    "efficiencies": {
      "overall": 39.788,
      "offense": 47.425,
      "defense": 38.261,
      "specialTeams": 41.553
    }
  },
  {
    "year": 2014,
    "team": "Middle Tennessee",
    "conference": "Conference USA",
    "fpi": -6.881,
    "resumeRanks": {
      "strengthOfRecord": 86,
      "fpi": 92,
      "averageWinProbability": 83,
      "strengthOfSchedule": 96,
      "remainingStrengthOfSchedule": null,
      "gameControl": 88
    },
    "efficiencies": {
      "overall": 35.819,
      "offense": 41.839,
      "defense": 33.537,
      "specialTeams": 56.379
    }
  },
  {
    "year": 2014,
    "team": "Florida Atlantic",
    "conference": "Conference USA",
    "fpi": -11.982,
    "resumeRanks": {
      "strengthOfRecord": 115,
      "fpi": 111,
      "averageWinProbability": 115,
      "strengthOfSchedule": 88,
      "remainingStrengthOfSchedule": null,
      "gameControl": 113
    },
    "efficiencies": {
      "overall": 29.563,
      "offense": 37.956,
      "defense": 28.732,
      "specialTeams": 50.476
    }
  },
  {
    "year": 2014,
    "team": "Florida International",
    "conference": "Conference USA",
    "fpi": -12.247,
    "resumeRanks": {
      "strengthOfRecord": 113,
      "fpi": 113,
      "averageWinProbability": 80,
      "strengthOfSchedule": 112,
      "remainingStrengthOfSchedule": null,
      "gameControl": 106
    },
    "efficiencies": {
      "overall": 31.841,
      "offense": 14.191,
      "defense": 61.517,
      "specialTeams": 47.24
    }
  },
  {
    "year": 2014,
    "team": "North Texas",
    "conference": "Conference USA",
    "fpi": -12.816,
    "resumeRanks": {
      "strengthOfRecord": 116,
      "fpi": 114,
      "averageWinProbability": 100,
      "strengthOfSchedule": 119,
      "remainingStrengthOfSchedule": null,
      "gameControl": 117
    },
    "efficiencies": {
      "overall": 20.129,
      "offense": 18.362,
      "defense": 29.374,
      "specialTeams": 57.137
    }
  },
  {
    "year": 2014,
    "team": "UTSA",
    "conference": "Conference USA",
    "fpi": -10.428,
    "resumeRanks": {
      "strengthOfRecord": 106,
      "fpi": 103,
      "averageWinProbability": 94,
      "strengthOfSchedule": 91,
      "remainingStrengthOfSchedule": null,
      "gameControl": 103
    },
    "efficiencies": {
      "overall": 26.841,
      "offense": 15.901,
      "defense": 49.296,
      "specialTeams": 49.213
    }
  },
  {
    "year": 2014,
    "team": "Louisiana Tech",
    "conference": "Conference USA",
    "fpi": 4.971,
    "resumeRanks": {
      "strengthOfRecord": 56,
      "fpi": 53,
      "averageWinProbability": 18,
      "strengthOfSchedule": 86,
      "remainingStrengthOfSchedule": null,
      "gameControl": 35
    },
    "efficiencies": {
      "overall": 62.346,
      "offense": 50.153,
      "defense": 69.526,
      "specialTeams": 48.912
    }
  },
  {
    "year": 2014,
    "team": "Western Kentucky",
    "conference": "Conference USA",
    "fpi": -3.009,
    "resumeRanks": {
      "strengthOfRecord": 75,
      "fpi": 83,
      "averageWinProbability": 27,
      "strengthOfSchedule": 105,
      "remainingStrengthOfSchedule": null,
      "gameControl": 61
    },
    "efficiencies": {
      "overall": 51,
      "offense": 76.05,
      "defense": 27.452,
      "specialTeams": 44.938
    }
  },
  {
    "year": 2014,
    "team": "Louisiana",
    "conference": "Sun Belt",
    "fpi": -2.553,
    "resumeRanks": {
      "strengthOfRecord": 57,
      "fpi": 80,
      "averageWinProbability": 48,
      "strengthOfSchedule": 107,
      "remainingStrengthOfSchedule": null,
      "gameControl": 73
    },
    "efficiencies": {
      "overall": 42.499,
      "offense": 51.021,
      "defense": 36.258,
      "specialTeams": 52.743
    }
  },
  {
    "year": 2014,
    "team": "Arkansas State",
    "conference": "Sun Belt",
    "fpi": -2.726,
    "resumeRanks": {
      "strengthOfRecord": 87,
      "fpi": 82,
      "averageWinProbability": 81,
      "strengthOfSchedule": 109,
      "remainingStrengthOfSchedule": null,
      "gameControl": 96
    },
    "efficiencies": {
      "overall": 39.756,
      "offense": 41.994,
      "defense": 42.229,
      "specialTeams": 47.325
    }
  },
  {
    "year": 2014,
    "team": "UL Monroe",
    "conference": "Sun Belt",
    "fpi": -9.928,
    "resumeRanks": {
      "strengthOfRecord": 104,
      "fpi": 101,
      "averageWinProbability": 92,
      "strengthOfSchedule": 83,
      "remainingStrengthOfSchedule": null,
      "gameControl": 89
    },
    "efficiencies": {
      "overall": 32.865,
      "offense": 20.097,
      "defense": 54.246,
      "specialTeams": 52.676
    }
  },
  {
    "year": 2014,
    "team": "Troy",
    "conference": "Sun Belt",
    "fpi": -19.383,
    "resumeRanks": {
      "strengthOfRecord": 119,
      "fpi": 124,
      "averageWinProbability": 105,
      "strengthOfSchedule": 111,
      "remainingStrengthOfSchedule": null,
      "gameControl": 117
    },
    "efficiencies": {
      "overall": 16.94,
      "offense": 29.487,
      "defense": 17.033,
      "specialTeams": 45.401
    }
  },
  {
    "year": 2014,
    "team": "South Alabama",
    "conference": "Sun Belt",
    "fpi": -9.353,
    "resumeRanks": {
      "strengthOfRecord": 97,
      "fpi": 98,
      "averageWinProbability": 84,
      "strengthOfSchedule": 99,
      "remainingStrengthOfSchedule": null,
      "gameControl": 98
    },
    "efficiencies": {
      "overall": 30.128,
      "offense": 21.551,
      "defense": 46.785,
      "specialTeams": 53.08
    }
  },
  {
    "year": 2014,
    "team": "Texas State",
    "conference": "Sun Belt",
    "fpi": -8.221,
    "resumeRanks": {
      "strengthOfRecord": 92,
      "fpi": 93,
      "averageWinProbability": 55,
      "strengthOfSchedule": 127,
      "remainingStrengthOfSchedule": null,
      "gameControl": 104
    },
    "efficiencies": {
      "overall": 34.248,
      "offense": 38.463,
      "defense": 31.993,
      "specialTeams": 62.159
    }
  },
  {
    "year": 2014,
    "team": "Georgia State",
    "conference": "Sun Belt",
    "fpi": -23.469,
    "resumeRanks": {
      "strengthOfRecord": 127,
      "fpi": 127,
      "averageWinProbability": 125,
      "strengthOfSchedule": 98,
      "remainingStrengthOfSchedule": null,
      "gameControl": 117
    },
    "efficiencies": {
      "overall": 12.404,
      "offense": 32.965,
      "defense": 9.72,
      "specialTeams": 36.711
    }
  },
  {
    "year": 2014,
    "team": "Georgia Southern",
    "conference": "Sun Belt",
    "fpi": 0.078,
    "resumeRanks": {
      "strengthOfRecord": 51,
      "fpi": 71,
      "averageWinProbability": 13,
      "strengthOfSchedule": 122,
      "remainingStrengthOfSchedule": null,
      "gameControl": 48
    },
    "efficiencies": {
      "overall": 60.911,
      "offense": 70.589,
      "defense": 48.093,
      "specialTeams": 47.18
    }
  },
  {
    "year": 2014,
    "team": "App State",
    "conference": "Sun Belt",
    "fpi": -5.62,
    "resumeRanks": {
      "strengthOfRecord": 88,
      "fpi": 89,
      "averageWinProbability": 65,
      "strengthOfSchedule": 125,
      "remainingStrengthOfSchedule": null,
      "gameControl": 102
    },
    "efficiencies": {
      "overall": 36.914,
      "offense": 51.496,
      "defense": 33.29,
      "specialTeams": 30.438
    }
  },
  {
    "year": 2014,
    "team": "Alabama",
    "conference": "SEC",
    "fpi": 26.766,
    "resumeRanks": {
      "strengthOfRecord": 2,
      "fpi": 2,
      "averageWinProbability": 8,
      "strengthOfSchedule": 4,
      "remainingStrengthOfSchedule": null,
      "gameControl": 3
    },
    "efficiencies": {
      "overall": 87.324,
      "offense": 84.903,
      "defense": 82.505,
      "specialTeams": 37.989
    }
  },
  {
    "year": 2014,
    "team": "Ole Miss",
    "conference": "SEC",
    "fpi": 20.488,
    "resumeRanks": {
      "strengthOfRecord": 12,
      "fpi": 9,
      "averageWinProbability": 21,
      "strengthOfSchedule": 5,
      "remainingStrengthOfSchedule": null,
      "gameControl": 12
    },
    "efficiencies": {
      "overall": 81.699,
      "offense": 61.049,
      "defense": 88.464,
      "specialTeams": 47.387
    }
  },
  {
    "year": 2014,
    "team": "Mississippi State",
    "conference": "SEC",
    "fpi": 20.133,
    "resumeRanks": {
      "strengthOfRecord": 10,
      "fpi": 10,
      "averageWinProbability": 10,
      "strengthOfSchedule": 44,
      "remainingStrengthOfSchedule": null,
      "gameControl": 10
    },
    "efficiencies": {
      "overall": 80.442,
      "offense": 77.232,
      "defense": 74.623,
      "specialTeams": 47.352
    }
  },
  {
    "year": 2014,
    "team": "Arkansas",
    "conference": "SEC",
    "fpi": 17.506,
    "resumeRanks": {
      "strengthOfRecord": 28,
      "fpi": 17,
      "averageWinProbability": 15,
      "strengthOfSchedule": 3,
      "remainingStrengthOfSchedule": null,
      "gameControl": 8
    },
    "efficiencies": {
      "overall": 81.732,
      "offense": 71.963,
      "defense": 78.766,
      "specialTeams": 60.727
    }
  },
  {
    "year": 2014,
    "team": "Western Michigan",
    "conference": "Mid-American",
    "fpi": -2.169,
    "resumeRanks": {
      "strengthOfRecord": 77,
      "fpi": 78,
      "averageWinProbability": 42,
      "strengthOfSchedule": 117,
      "remainingStrengthOfSchedule": null,
      "gameControl": 77
    },
    "efficiencies": {
      "overall": 52.624,
      "offense": 59.668,
      "defense": 46.37,
      "specialTeams": 45.427
    }
  },
  {
    "year": 2014,
    "team": "Ball State",
    "conference": "Mid-American",
    "fpi": -8.364,
    "resumeRanks": {
      "strengthOfRecord": 105,
      "fpi": 95,
      "averageWinProbability": 68,
      "strengthOfSchedule": 123,
      "remainingStrengthOfSchedule": null,
      "gameControl": 99
    },
    "efficiencies": {
      "overall": 35.7,
      "offense": 34.209,
      "defense": 38.332,
      "specialTeams": 62.344
    }
  },
  {
    "year": 2014,
    "team": "Eastern Michigan",
    "conference": "Mid-American",
    "fpi": -25.824,
    "resumeRanks": {
      "strengthOfRecord": 123,
      "fpi": 128,
      "averageWinProbability": 127,
      "strengthOfSchedule": 93,
      "remainingStrengthOfSchedule": null,
      "gameControl": 117
    },
    "efficiencies": {
      "overall": 8.723,
      "offense": 11.315,
      "defense": 16.48,
      "specialTeams": 46.844
    }
  },
  {
    "year": 2014,
    "team": "Central Michigan",
    "conference": "Mid-American",
    "fpi": -4.965,
    "resumeRanks": {
      "strengthOfRecord": 89,
      "fpi": 87,
      "averageWinProbability": 62,
      "strengthOfSchedule": 115,
      "remainingStrengthOfSchedule": null,
      "gameControl": 92
    },
    "efficiencies": {
      "overall": 40.518,
      "offense": 44.014,
      "defense": 45.405,
      "specialTeams": 35.234
    }
  },
  {
    "year": 2014,
    "team": "Northern Illinois",
    "conference": "Mid-American",
    "fpi": 0.248,
    "resumeRanks": {
      "strengthOfRecord": 42,
      "fpi": 70,
      "averageWinProbability": 46,
      "strengthOfSchedule": 108,
      "remainingStrengthOfSchedule": null,
      "gameControl": 75
    },
    "efficiencies": {
      "overall": 46.624,
      "offense": 51.83,
      "defense": 39.848,
      "specialTeams": 58.223
    }
  },
  {
    "year": 2014,
    "team": "Marshall",
    "conference": "Conference USA",
    "fpi": 13.025,
    "resumeRanks": {
      "strengthOfRecord": 26,
      "fpi": 29,
      "averageWinProbability": 3,
      "strengthOfSchedule": 126,
      "remainingStrengthOfSchedule": null,
      "gameControl": 40
    },
    "efficiencies": {
      "overall": 69.161,
      "offense": 71.662,
      "defense": 58.119,
      "specialTeams": 55.611
    }
  },
  {
    "year": 2014,
    "team": "Old Dominion",
    "conference": "Conference USA",
    "fpi": -11.442,
    "resumeRanks": {
      "strengthOfRecord": 91,
      "fpi": 108,
      "averageWinProbability": 97,
      "strengthOfSchedule": 106,
      "remainingStrengthOfSchedule": null,
      "gameControl": 115
    },
    "efficiencies": {
      "overall": 27.175,
      "offense": 60.064,
      "defense": 16.208,
      "specialTeams": 24.663
    }
  },
  {
    "year": 2014,
    "team": "Southern Miss",
    "conference": "Conference USA",
    "fpi": -14.949,
    "resumeRanks": {
      "strengthOfRecord": 110,
      "fpi": 120,
      "averageWinProbability": 116,
      "strengthOfSchedule": 75,
      "remainingStrengthOfSchedule": null,
      "gameControl": 114
    },
    "efficiencies": {
      "overall": 21.937,
      "offense": 24.881,
      "defense": 26.99,
      "specialTeams": 55.002
    }
  },
  {
    "year": 2014,
    "team": "Buffalo",
    "conference": "Mid-American",
    "fpi": -10.921,
    "resumeRanks": {
      "strengthOfRecord": 108,
      "fpi": 107,
      "averageWinProbability": 77,
      "strengthOfSchedule": 128,
      "remainingStrengthOfSchedule": null,
      "gameControl": 108
    },
    "efficiencies": {
      "overall": 25.04,
      "offense": 39.942,
      "defense": 22.899,
      "specialTeams": 35.043
    }
  },
  {
    "year": 2014,
    "team": "Florida State",
    "conference": "ACC",
    "fpi": 19.025,
    "resumeRanks": {
      "strengthOfRecord": 3,
      "fpi": 14,
      "averageWinProbability": 37,
      "strengthOfSchedule": 24,
      "remainingStrengthOfSchedule": null,
      "gameControl": 26
    },
    "efficiencies": {
      "overall": 74.8,
      "offense": 76.33,
      "defense": 62.939,
      "specialTeams": 55.013
    }
  },
  {
    "year": 2014,
    "team": "Boston College",
    "conference": "ACC",
    "fpi": 6.034,
    "resumeRanks": {
      "strengthOfRecord": 55,
      "fpi": 51,
      "averageWinProbability": 33,
      "strengthOfSchedule": 58,
      "remainingStrengthOfSchedule": null,
      "gameControl": 39
    },
    "efficiencies": {
      "overall": 60.952,
      "offense": 63.653,
      "defense": 54.322,
      "specialTeams": 49.104
    }
  },
  {
    "year": 2014,
    "team": "Clemson",
    "conference": "ACC",
    "fpi": 16.461,
    "resumeRanks": {
      "strengthOfRecord": 16,
      "fpi": 20,
      "averageWinProbability": 9,
      "strengthOfSchedule": 50,
      "remainingStrengthOfSchedule": null,
      "gameControl": 13
    },
    "efficiencies": {
      "overall": 75.832,
      "offense": 49.562,
      "defense": 92.5,
      "specialTeams": 32.101
    }
  },
  {
    "year": 2014,
    "team": "NC State",
    "conference": "ACC",
    "fpi": 3.924,
    "resumeRanks": {
      "strengthOfRecord": 47,
      "fpi": 58,
      "averageWinProbability": 54,
      "strengthOfSchedule": 66,
      "remainingStrengthOfSchedule": null,
      "gameControl": 54
    },
    "efficiencies": {
      "overall": 56.087,
      "offense": 62.787,
      "defense": 44.737,
      "specialTeams": 56.589
    }
  },
  {
    "year": 2014,
    "team": "Wake Forest",
    "conference": "ACC",
    "fpi": -10.446,
    "resumeRanks": {
      "strengthOfRecord": 102,
      "fpi": 104,
      "averageWinProbability": 109,
      "strengthOfSchedule": 61,
      "remainingStrengthOfSchedule": null,
      "gameControl": 91
    },
    "efficiencies": {
      "overall": 30.148,
      "offense": 12.21,
      "defense": 53.432,
      "specialTeams": 67.815
    }
  },
  {
    "year": 2014,
    "team": "Virginia Tech",
    "conference": "ACC",
    "fpi": 7.869,
    "resumeRanks": {
      "strengthOfRecord": 52,
      "fpi": 41,
      "averageWinProbability": 59,
      "strengthOfSchedule": 49,
      "remainingStrengthOfSchedule": null,
      "gameControl": 51
    },
    "efficiencies": {
      "overall": 58.405,
      "offense": 30.098,
      "defense": 81.975,
      "specialTeams": 55.003
    }
  },
  {
    "year": 2014,
    "team": "Miami",
    "conference": "ACC",
    "fpi": 10.774,
    "resumeRanks": {
      "strengthOfRecord": 58,
      "fpi": 36,
      "averageWinProbability": 38,
      "strengthOfSchedule": 31,
      "remainingStrengthOfSchedule": null,
      "gameControl": 27
    },
    "efficiencies": {
      "overall": 66.131,
      "offense": 63.094,
      "defense": 65.789,
      "specialTeams": 41.832
    }
  },
  {
    "year": 2014,
    "team": "Georgia Tech",
    "conference": "ACC",
    "fpi": 15.985,
    "resumeRanks": {
      "strengthOfRecord": 13,
      "fpi": 21,
      "averageWinProbability": 25,
      "strengthOfSchedule": 25,
      "remainingStrengthOfSchedule": null,
      "gameControl": 19
    },
    "efficiencies": {
      "overall": 78.496,
      "offense": 89.562,
      "defense": 50.493,
      "specialTeams": 44.695
    }
  },
  {
    "year": 2014,
    "team": "North Carolina",
    "conference": "ACC",
    "fpi": 4.371,
    "resumeRanks": {
      "strengthOfRecord": 64,
      "fpi": 57,
      "averageWinProbability": 112,
      "strengthOfSchedule": 34,
      "remainingStrengthOfSchedule": null,
      "gameControl": 85
    },
    "efficiencies": {
      "overall": 45.718,
      "offense": 60.663,
      "defense": 33.282,
      "specialTeams": 48.175
    }
  },
  {
    "year": 2014,
    "team": "Virginia",
    "conference": "ACC",
    "fpi": 6.897,
    "resumeRanks": {
      "strengthOfRecord": 66,
      "fpi": 46,
      "averageWinProbability": 66,
      "strengthOfSchedule": 30,
      "remainingStrengthOfSchedule": null,
      "gameControl": 46
    },
    "efficiencies": {
      "overall": 56.153,
      "offense": 37.634,
      "defense": 71.372,
      "specialTeams": 53.007
    }
  },
  {
    "year": 2014,
    "team": "Duke",
    "conference": "ACC",
    "fpi": 7.678,
    "resumeRanks": {
      "strengthOfRecord": 40,
      "fpi": 42,
      "averageWinProbability": 30,
      "strengthOfSchedule": 68,
      "remainingStrengthOfSchedule": null,
      "gameControl": 42
    },
    "efficiencies": {
      "overall": 60.574,
      "offense": 60.564,
      "defense": 49.34,
      "specialTeams": 72.395
    }
  },
  {
    "year": 2014,
    "team": "Bowling Green",
    "conference": "Mid-American",
    "fpi": -9.42,
    "resumeRanks": {
      "strengthOfRecord": 83,
      "fpi": 99,
      "averageWinProbability": 70,
      "strengthOfSchedule": 110,
      "remainingStrengthOfSchedule": null,
      "gameControl": 95
    },
    "efficiencies": {
      "overall": 34.023,
      "offense": 32.156,
      "defense": 38.672,
      "specialTeams": 60.3
    }
  },
  {
    "year": 2014,
    "team": "Missouri",
    "conference": "SEC",
    "fpi": 13.651,
    "resumeRanks": {
      "strengthOfRecord": 9,
      "fpi": 26,
      "averageWinProbability": 39,
      "strengthOfSchedule": 16,
      "remainingStrengthOfSchedule": null,
      "gameControl": 21
    },
    "efficiencies": {
      "overall": 71.744,
      "offense": 58.841,
      "defense": 74.962,
      "specialTeams": 53.999
    }
  },
  {
    "year": 2014,
    "team": "Texas A&M",
    "conference": "SEC",
    "fpi": 14.96,
    "resumeRanks": {
      "strengthOfRecord": 23,
      "fpi": 23,
      "averageWinProbability": 56,
      "strengthOfSchedule": 15,
      "remainingStrengthOfSchedule": null,
      "gameControl": 25
    },
    "efficiencies": {
      "overall": 68.73,
      "offense": 79.059,
      "defense": 44.225,
      "specialTeams": 72.235
    }
  },
  {
    "year": 2014,
    "team": "Syracuse",
    "conference": "ACC",
    "fpi": -0.773,
    "resumeRanks": {
      "strengthOfRecord": 94,
      "fpi": 73,
      "averageWinProbability": 107,
      "strengthOfSchedule": 40,
      "remainingStrengthOfSchedule": null,
      "gameControl": 87
    },
    "efficiencies": {
      "overall": 39.01,
      "offense": 24.063,
      "defense": 63.581,
      "specialTeams": 38.141
    }
  },
  {
    "year": 2014,
    "team": "Pittsburgh",
    "conference": "ACC",
    "fpi": 7.202,
    "resumeRanks": {
      "strengthOfRecord": 74,
      "fpi": 45,
      "averageWinProbability": 40,
      "strengthOfSchedule": 62,
      "remainingStrengthOfSchedule": null,
      "gameControl": 45
    },
    "efficiencies": {
      "overall": 57.007,
      "offense": 71.254,
      "defense": 39.396,
      "specialTeams": 45.964
    }
  },
  {
    "year": 2014,
    "team": "Utah State",
    "conference": "Mountain West",
    "fpi": 1.86,
    "resumeRanks": {
      "strengthOfRecord": 49,
      "fpi": 65,
      "averageWinProbability": 16,
      "strengthOfSchedule": 95,
      "remainingStrengthOfSchedule": null,
      "gameControl": 38
    },
    "efficiencies": {
      "overall": 58.177,
      "offense": 34.322,
      "defense": 74.051,
      "specialTeams": 49.668
    }
  },
  {
    "year": 2014,
    "team": "Boise State",
    "conference": "Mountain West",
    "fpi": 10.739,
    "resumeRanks": {
      "strengthOfRecord": 24,
      "fpi": 37,
      "averageWinProbability": 11,
      "strengthOfSchedule": 77,
      "remainingStrengthOfSchedule": null,
      "gameControl": 34
    },
    "efficiencies": {
      "overall": 68.41,
      "offense": 68.171,
      "defense": 65.073,
      "specialTeams": 40.388
    }
  },
  {
    "year": 2014,
    "team": "Colorado State",
    "conference": "Mountain West",
    "fpi": 2.414,
    "resumeRanks": {
      "strengthOfRecord": 39,
      "fpi": 63,
      "averageWinProbability": 36,
      "strengthOfSchedule": 92,
      "remainingStrengthOfSchedule": null,
      "gameControl": 60
    },
    "efficiencies": {
      "overall": 59.201,
      "offense": 73.878,
      "defense": 40.313,
      "specialTeams": 52.513
    }
  },
  {
    "year": 2014,
    "team": "Wyoming",
    "conference": "Mountain West",
    "fpi": -11.516,
    "resumeRanks": {
      "strengthOfRecord": 100,
      "fpi": 109,
      "averageWinProbability": 108,
      "strengthOfSchedule": 72,
      "remainingStrengthOfSchedule": null,
      "gameControl": 107
    },
    "efficiencies": {
      "overall": 23.617,
      "offense": 30.879,
      "defense": 31.178,
      "specialTeams": 30.161
    }
  },
  {
    "year": 2014,
    "team": "New Mexico",
    "conference": "Mountain West",
    "fpi": -12.122,
    "resumeRanks": {
      "strengthOfRecord": 109,
      "fpi": 112,
      "averageWinProbability": 102,
      "strengthOfSchedule": 94,
      "remainingStrengthOfSchedule": null,
      "gameControl": 110
    },
    "efficiencies": {
      "overall": 27.479,
      "offense": 51.673,
      "defense": 17.127,
      "specialTeams": 56.409
    }
  },
  {
    "year": 2014,
    "team": "Air Force",
    "conference": "Mountain West",
    "fpi": -2.584,
    "resumeRanks": {
      "strengthOfRecord": 48,
      "fpi": 81,
      "averageWinProbability": 20,
      "strengthOfSchedule": 113,
      "remainingStrengthOfSchedule": null,
      "gameControl": 66
    },
    "efficiencies": {
      "overall": 48.39,
      "offense": 41.923,
      "defense": 51.43,
      "specialTeams": 63.268
    }
  },
  {
    "year": 2014,
    "team": "Fresno State",
    "conference": "Mountain West",
    "fpi": -5.318,
    "resumeRanks": {
      "strengthOfRecord": 90,
      "fpi": 88,
      "averageWinProbability": 101,
      "strengthOfSchedule": 73,
      "remainingStrengthOfSchedule": null,
      "gameControl": 97
    },
    "efficiencies": {
      "overall": 33.645,
      "offense": 34.386,
      "defense": 38.153,
      "specialTeams": 52.625
    }
  },
  {
    "year": 2014,
    "team": "San Diego State",
    "conference": "Mountain West",
    "fpi": -2.034,
    "resumeRanks": {
      "strengthOfRecord": 85,
      "fpi": 77,
      "averageWinProbability": 24,
      "strengthOfSchedule": 104,
      "remainingStrengthOfSchedule": null,
      "gameControl": 57
    },
    "efficiencies": {
      "overall": 48.224,
      "offense": 37.842,
      "defense": 56.807,
      "specialTeams": 56.769
    }
  },
  {
    "year": 2014,
    "team": "UNLV",
    "conference": "Mountain West",
    "fpi": -17.372,
    "resumeRanks": {
      "strengthOfRecord": 124,
      "fpi": 122,
      "averageWinProbability": 119,
      "strengthOfSchedule": 79,
      "remainingStrengthOfSchedule": null,
      "gameControl": 117
    },
    "efficiencies": {
      "overall": 18.977,
      "offense": 28.556,
      "defense": 17.666,
      "specialTeams": 57.377
    }
  },
  {
    "year": 2014,
    "team": "San José State",
    "conference": "Mountain West",
    "fpi": -11.723,
    "resumeRanks": {
      "strengthOfRecord": 112,
      "fpi": 110,
      "averageWinProbability": 110,
      "strengthOfSchedule": 74,
      "remainingStrengthOfSchedule": null,
      "gameControl": 109
    },
    "efficiencies": {
      "overall": 24.373,
      "offense": 32.47,
      "defense": 34.47,
      "specialTeams": 19.883
    }
  },
  {
    "year": 2014,
    "team": "Nevada",
    "conference": "Mountain West",
    "fpi": -0.274,
    "resumeRanks": {
      "strengthOfRecord": 76,
      "fpi": 72,
      "averageWinProbability": 91,
      "strengthOfSchedule": 78,
      "remainingStrengthOfSchedule": null,
      "gameControl": 94
    },
    "efficiencies": {
      "overall": 45.671,
      "offense": 44.299,
      "defense": 45.762,
      "specialTeams": 59.298
    }
  },
  {
    "year": 2014,
    "team": "Hawai'i",
    "conference": "Mountain West",
    "fpi": -9.087,
    "resumeRanks": {
      "strengthOfRecord": 111,
      "fpi": 96,
      "averageWinProbability": 111,
      "strengthOfSchedule": 85,
      "remainingStrengthOfSchedule": null,
      "gameControl": 117
    },
    "efficiencies": {
      "overall": 28.643,
      "offense": 22.914,
      "defense": 36.176,
      "specialTeams": 69.708
    }
  },
  {
    "year": 2014,
    "team": "Louisville",
    "conference": "ACC",
    "fpi": 10.966,
    "resumeRanks": {
      "strengthOfRecord": 27,
      "fpi": 35,
      "averageWinProbability": 34,
      "strengthOfSchedule": 47,
      "remainingStrengthOfSchedule": null,
      "gameControl": 29
    },
    "efficiencies": {
      "overall": 68.862,
      "offense": 49.161,
      "defense": 84.982,
      "specialTeams": 35.315
    }
  },
  {
    "year": 2014,
    "team": "Ohio State",
    "conference": "Big Ten",
    "fpi": 25.734,
    "resumeRanks": {
      "strengthOfRecord": 1,
      "fpi": 4,
      "averageWinProbability": 7,
      "strengthOfSchedule": 35,
      "remainingStrengthOfSchedule": null,
      "gameControl": 5
    },
    "efficiencies": {
      "overall": 87.474,
      "offense": 87.541,
      "defense": 74.927,
      "specialTeams": 53.352
    }
  },
  {
    "year": 2014,
    "team": "Michigan State",
    "conference": "Big Ten",
    "fpi": 23.051,
    "resumeRanks": {
      "strengthOfRecord": 6,
      "fpi": 7,
      "averageWinProbability": 5,
      "strengthOfSchedule": 53,
      "remainingStrengthOfSchedule": null,
      "gameControl": 7
    },
    "efficiencies": {
      "overall": 85.682,
      "offense": 83.245,
      "defense": 76.16,
      "specialTeams": 54.451
    }
  },
  {
    "year": 2014,
    "team": "Maryland",
    "conference": "Big Ten",
    "fpi": 5.77,
    "resumeRanks": {
      "strengthOfRecord": 44,
      "fpi": 52,
      "averageWinProbability": 85,
      "strengthOfSchedule": 32,
      "remainingStrengthOfSchedule": null,
      "gameControl": 59
    },
    "efficiencies": {
      "overall": 58.02,
      "offense": 45.395,
      "defense": 59.648,
      "specialTeams": 67.109
    }
  },
  {
    "year": 2014,
    "team": "Rutgers",
    "conference": "Big Ten",
    "fpi": 1.517,
    "resumeRanks": {
      "strengthOfRecord": 36,
      "fpi": 67,
      "averageWinProbability": 73,
      "strengthOfSchedule": 42,
      "remainingStrengthOfSchedule": null,
      "gameControl": 50
    },
    "efficiencies": {
      "overall": 53.554,
      "offense": 60.731,
      "defense": 42.859,
      "specialTeams": 57.873
    }
  },
  {
    "year": 2014,
    "team": "Michigan",
    "conference": "Big Ten",
    "fpi": 7.222,
    "resumeRanks": {
      "strengthOfRecord": 70,
      "fpi": 44,
      "averageWinProbability": 75,
      "strengthOfSchedule": 43,
      "remainingStrengthOfSchedule": null,
      "gameControl": 53
    },
    "efficiencies": {
      "overall": 49.661,
      "offense": 34.668,
      "defense": 65.686,
      "specialTeams": 44.171
    }
  },
  {
    "year": 2014,
    "team": "Penn State",
    "conference": "Big Ten",
    "fpi": 4.594,
    "resumeRanks": {
      "strengthOfRecord": 63,
      "fpi": 56,
      "averageWinProbability": 71,
      "strengthOfSchedule": 64,
      "remainingStrengthOfSchedule": null,
      "gameControl": 68
    },
    "efficiencies": {
      "overall": 53.074,
      "offense": 26.804,
      "defense": 82.396,
      "specialTeams": 40.589
    }
  },
  {
    "year": 2014,
    "team": "Indiana",
    "conference": "Big Ten",
    "fpi": -0.816,
    "resumeRanks": {
      "strengthOfRecord": 84,
      "fpi": 74,
      "averageWinProbability": 96,
      "strengthOfSchedule": 56,
      "remainingStrengthOfSchedule": null,
      "gameControl": 76
    },
    "efficiencies": {
      "overall": 42.495,
      "offense": 44.399,
      "defense": 46.51,
      "specialTeams": 41.145
    }
  },
  {
    "year": 2014,
    "team": "Wisconsin",
    "conference": "Big Ten",
    "fpi": 17.072,
    "resumeRanks": {
      "strengthOfRecord": 18,
      "fpi": 19,
      "averageWinProbability": 17,
      "strengthOfSchedule": 57,
      "remainingStrengthOfSchedule": null,
      "gameControl": 20
    },
    "efficiencies": {
      "overall": 74.792,
      "offense": 76.184,
      "defense": 68.52,
      "specialTeams": 38.718
    }
  },
  {
    "year": 2014,
    "team": "Minnesota",
    "conference": "Big Ten",
    "fpi": 8.32,
    "resumeRanks": {
      "strengthOfRecord": 34,
      "fpi": 39,
      "averageWinProbability": 53,
      "strengthOfSchedule": 51,
      "remainingStrengthOfSchedule": null,
      "gameControl": 41
    },
    "efficiencies": {
      "overall": 62.265,
      "offense": 59.26,
      "defense": 56.474,
      "specialTeams": 62.827
    }
  },
  {
    "year": 2014,
    "team": "Nebraska",
    "conference": "Big Ten",
    "fpi": 13.173,
    "resumeRanks": {
      "strengthOfRecord": 32,
      "fpi": 28,
      "averageWinProbability": 26,
      "strengthOfSchedule": 63,
      "remainingStrengthOfSchedule": null,
      "gameControl": 30
    },
    "efficiencies": {
      "overall": 68.053,
      "offense": 60.749,
      "defense": 58.327,
      "specialTeams": 78.713
    }
  },
  {
    "year": 2014,
    "team": "Iowa",
    "conference": "Big Ten",
    "fpi": 6.368,
    "resumeRanks": {
      "strengthOfRecord": 61,
      "fpi": 49,
      "averageWinProbability": 74,
      "strengthOfSchedule": 59,
      "remainingStrengthOfSchedule": null,
      "gameControl": 67
    },
    "efficiencies": {
      "overall": 50.959,
      "offense": 51.324,
      "defense": 57.133,
      "specialTeams": 32.15
    }
  },
  {
    "year": 2014,
    "team": "Illinois",
    "conference": "Big Ten",
    "fpi": -2.476,
    "resumeRanks": {
      "strengthOfRecord": 69,
      "fpi": 79,
      "averageWinProbability": 99,
      "strengthOfSchedule": 55,
      "remainingStrengthOfSchedule": null,
      "gameControl": 82
    },
    "efficiencies": {
      "overall": 40.884,
      "offense": 40.905,
      "defense": 41.939,
      "specialTeams": 56.462
    }
  },
  {
    "year": 2014,
    "team": "Northwestern",
    "conference": "Big Ten",
    "fpi": 1.819,
    "resumeRanks": {
      "strengthOfRecord": 72,
      "fpi": 66,
      "averageWinProbability": 86,
      "strengthOfSchedule": 46,
      "remainingStrengthOfSchedule": null,
      "gameControl": 69
    },
    "efficiencies": {
      "overall": 46.832,
      "offense": 32.133,
      "defense": 63.749,
      "specialTeams": 51.428
    }
  },
  {
    "year": 2014,
    "team": "Purdue",
    "conference": "Big Ten",
    "fpi": -3.959,
    "resumeRanks": {
      "strengthOfRecord": 98,
      "fpi": 86,
      "averageWinProbability": 98,
      "strengthOfSchedule": 52,
      "remainingStrengthOfSchedule": null,
      "gameControl": 83
    },
    "efficiencies": {
      "overall": 39.858,
      "offense": 35.242,
      "defense": 46.475,
      "specialTeams": 53.876
    }
  },
  {
    "year": 2014,
    "team": "Army",
    "conference": "FBS Independents",
    "fpi": -14.056,
    "resumeRanks": {
      "strengthOfRecord": 114,
      "fpi": 116,
      "averageWinProbability": 78,
      "strengthOfSchedule": 116,
      "remainingStrengthOfSchedule": null,
      "gameControl": 100
    },
    "efficiencies": {
      "overall": 26.982,
      "offense": 41.386,
      "defense": 22.323,
      "specialTeams": 49.823
    }
  },
  {
    "year": 2014,
    "team": "Texas",
    "conference": "Big 12",
    "fpi": 8.78,
    "resumeRanks": {
      "strengthOfRecord": 46,
      "fpi": 38,
      "averageWinProbability": 79,
      "strengthOfSchedule": 11,
      "remainingStrengthOfSchedule": null,
      "gameControl": 44
    },
    "efficiencies": {
      "overall": 59.583,
      "offense": 33.545,
      "defense": 81.921,
      "specialTeams": 37.267
    }
  },
  {
    "year": 2014,
    "team": "Oklahoma",
    "conference": "Big 12",
    "fpi": 18.901,
    "resumeRanks": {
      "strengthOfRecord": 30,
      "fpi": 16,
      "averageWinProbability": 23,
      "strengthOfSchedule": 21,
      "remainingStrengthOfSchedule": null,
      "gameControl": 16
    },
    "efficiencies": {
      "overall": 78.048,
      "offense": 76.408,
      "defense": 69.539,
      "specialTeams": 53.98
    }
  }
]