[
  {
    "year": 2025,
    "team": "Indiana",
    "conference": "Big Ten",
    "division": null,
    "ranking": 1,
    "rating": 27.3
  },
  {
    "year": 2025,
    "team": "Ohio State",
    "conference": "Big Ten",
    "division": null,
    "ranking": 2,
    "rating": 26.6
  },
  {
    "year": 2025,
    "team": "Notre Dame",
    "conference": "FBS Independents",
    "division": null,
    "ranking": 3,
    "rating": 24.1
  },
  {
    "year": 2025,
    "team": "Texas Tech",
    "conference": "Big 12",
    "division": null,
    "ranking": 4,
    "rating": 22.3
  },
  {
    "year": 2025,
    "team": "Miami",
    "conference": "ACC",
    "division": null,
    "ranking": 5,
    "rating": 22.2
  },
  {
    "year": 2025,
    "team": "Oregon",
    "conference": "Big Ten",
    "division": null,
    "ranking": 6,
    "rating": 22.1
  },
  {
    "year": 2025,
    "team": "Utah",
    "conference": "Big 12",
    "division": null,
    "ranking": 7,
    "rating": 21.3
  },
  {
    "year": 2025,
    "team": "Washington",
    "conference": "Big Ten",
    "division": null,
    "ranking": 8,
    "rating": 17.4
  },
  {
    "year": 2025,
    "team": "Texas A&M",
    "conference": "SEC",
    "division": null,
    "ranking": 9,
    "rating": 16.6
  },
  {
    "year": 2025,
    "team": "Georgia",
    "conference": "SEC",
    "division": null,
    "ranking": 10,
    "rating": 16
  },
  {
    "year": 2025,
    "team": "Vanderbilt",
    "conference": "SEC",
    "division": null,
    "ranking": 10,
    "rating": 16
  },
  {
    "year": 2025,
    "team": "Ole Miss",
    "conference": "SEC",
    "division": null,
    "ranking": 12,
    "rating": 15.8
  },
  {
    "year": 2025,
    "team": "USC",
    "conference": "Big Ten",
    "division": null,
    "ranking": 13,
    "rating": 15.5
  },
  {
    "year": 2025,
    "team": "BYU",
    "conference": "Big 12",
    "division": null,
    "ranking": 14,
    "rating": 15
  },
  {
    "year": 2025,
    "team": "Penn State",
    "conference": "Big Ten",
    "division": null,
    "ranking": 15,
    "rating": 14.4
  },
  {
    "year": 2025,
    "team": "Iowa",
    "conference": "Big Ten",
    "division": null,
    "ranking": 16,
    "rating": 13.8
  },
  {
    "year": 2025,
    "team": "Alabama",
    "conference": "SEC",
    "division": null,
    "ranking": 17,
    "rating": 12.7
  },
  {
    "year": 2025,
    "team": "Oklahoma",
    "conference": "SEC",
    "division": null,
    "ranking": 17,
    "rating": 12.7
  },
  {
    "year": 2025,
    "team": "Texas",
    "conference": "SEC",
    "division": null,
    "ranking": 19,
    "rating": 12.6
  },
  {
    "year": 2025,
    "team": "South Florida",
    "conference": "American Athletic",
    "division": null,
    "ranking": 19,
    "rating": 12.6
  },
  {
    "year": 2025,
    "team": "Illinois",
    "conference": "Big Ten",
    "division": null,
    "ranking": 21,
    "rating": 12.3
  },
  {
    "year": 2025,
    "team": "Arizona",
    "conference": "Big 12",
    "division": null,
    "ranking": 22,
    "rating": 12.2
  },
  {
    "year": 2025,
    "team": "Tennessee",
    "conference": "SEC",
    "division": null,
    "ranking": 23,
    "rating": 11.7
  },
  {
    "year": 2025,
    "team": "Michigan",
    "conference": "Big Ten",
    "division": null,
    "ranking": 24,
    "rating": 11
  },
  {
    "year": 2025,
    "team": "SMU",
    "conference": "ACC",
    "division": null,
    "ranking": 24,
    "rating": 11
  },
  {
    "year": 2025,
    "team": "North Texas",
    "conference": "American Athletic",
    "division": null,
    "ranking": 26,
    "rating": 10.6
  },
  {
    "year": 2025,
    "team": "Missouri",
    "conference": "SEC",
    "division": null,
    "ranking": 27,
    "rating": 10.5
  },
  {
    "year": 2025,
    "team": "Pittsburgh",
    "conference": "ACC",
    "division": null,
    "ranking": 28,
    "rating": 10
  },
  {
    "year": 2025,
    "team": "James Madison",
    "conference": "Sun Belt",
    "division": "East",
    "ranking": 29,
    "rating": 9.9
  },
  {
    "year": 2025,
    "team": "Virginia",
    "conference": "ACC",
    "division": null,
    "ranking": 30,
    "rating": 9.8
  },
  {
    "year": 2025,
    "team": "Iowa State",
    "conference": "Big 12",
    "division": null,
    "ranking": 31,
    "rating": 9.6
  },
  {
    "year": 2025,
    "team": "Louisville",
    "conference": "ACC",
    "division": null,
    "ranking": 32,
    "rating": 9.3
  },
  {
    "year": 2025,
    "team": "TCU",
    "conference": "Big 12",
    "division": null,
    "ranking": 33,
    "rating": 8.5
  },
  {
    "year": 2025,
    "team": "Florida State",
    "conference": "ACC",
    "division": null,
    "ranking": 34,
    "rating": 8.4
  },
  {
    "year": 2025,
    "team": "Auburn",
    "conference": "SEC",
    "division": null,
    "ranking": 35,
    "rating": 8.3
  },
  {
    "year": 2025,
    "team": "LSU",
    "conference": "SEC",
    "division": null,
    "ranking": 36,
    "rating": 8.2
  },
  {
    "year": 2025,
    "team": "Georgia Tech",
    "conference": "ACC",
    "division": null,
    "ranking": 37,
    "rating": 7.8
  },
  {
    "year": 2025,
    "team": "Kansas State",
    "conference": "Big 12",
    "division": null,
    "ranking": 38,
    "rating": 7.2
  },
  {
    "year": 2025,
    "team": "NC State",
    "conference": "ACC",
    "division": null,
    "ranking": 39,
    "rating": 7
  },
  {
    "year": 2025,
    "team": "Houston",
    "conference": "Big 12",
    "division": null,
    "ranking": 40,
    "rating": 6.3
  },
  {
    "year": 2025,
    "team": "Toledo",
    "conference": "Mid-American",
    "division": null,
    "ranking": 41,
    "rating": 6.2
  },
  {
    "year": 2025,
    "team": "Washington State",
    "conference": "Pac-12",
    "division": null,
    "ranking": 41,
    "rating": 6.2
  },
  {
    "year": 2025,
    "team": "Clemson",
    "conference": "ACC",
    "division": null,
    "ranking": 41,
    "rating": 6.2
  },
  {
    "year": 2025,
    "team": "Old Dominion",
    "conference": "Sun Belt",
    "division": "East",
    "ranking": 44,
    "rating": 6.1
  },
  {
    "year": 2025,
    "team": "Arizona State",
    "conference": "Big 12",
    "division": null,
    "ranking": 45,
    "rating": 5.8
  },
  {
    "year": 2025,
    "team": "East Carolina",
    "conference": "American Athletic",
    "division": null,
    "ranking": 46,
    "rating": 5.7
  },
  {
    "year": 2025,
    "team": "Florida",
    "conference": "SEC",
    "division": null,
    "ranking": 47,
    "rating": 5.4
  },
  {
    "year": 2025,
    "team": "Duke",
    "conference": "ACC",
    "division": null,
    "ranking": 48,
    "rating": 5.2
  },
  {
    "year": 2025,
    "team": "Northwestern",
    "conference": "Big Ten",
    "division": null,
    "ranking": 49,
    "rating": 4.4
  },
  {
    "year": 2025,
    "team": "Boise State",
    "conference": "Mountain West",
    "division": null,
    "ranking": 50,
    "rating": 4.3
  },
  {
    "year": 2025,
    "team": "Wake Forest",
    "conference": "ACC",
    "division": null,
    "ranking": 51,
    "rating": 4.2
  },
  {
    "year": 2025,
    "team": "Arkansas",
    "conference": "SEC",
    "division": null,
    "ranking": 52,
    "rating": 4
  },
  {
    "year": 2025,
    "team": "South Carolina",
    "conference": "SEC",
    "division": null,
    "ranking": 53,
    "rating": 3.8
  },
  {
    "year": 2025,
    "team": "San Diego State",
    "conference": "Mountain West",
    "division": null,
    "ranking": 54,
    "rating": 3.6
  },
  {
    "year": 2025,
    "team": "Kansas",
    "conference": "Big 12",
    "division": null,
    "ranking": 55,
    "rating": 3.2
  },
  {
    "year": 2025,
    "team": "Tulane",
    "conference": "American Athletic",
    "division": null,
    "ranking": 56,
    "rating": 3
  },
  {
    "year": 2025,
    "team": "Kentucky",
    "conference": "SEC",
    "division": null,
    "ranking": 57,
    "rating": 2.9
  },
  {
    "year": 2025,
    "team": "Cincinnati",
    "conference": "Big 12",
    "division": null,
    "ranking": 57,
    "rating": 2.9
  },
  {
    "year": 2025,
    "team": "Nebraska",
    "conference": "Big Ten",
    "division": null,
    "ranking": 59,
    "rating": 2.5
  },
  {
    "year": 2025,
    "team": "Memphis",
    "conference": "American Athletic",
    "division": null,
    "ranking": 59,
    "rating": 2.5
  },
  {
    "year": 2025,
    "team": "Rutgers",
    "conference": "Big Ten",
    "division": null,
    "ranking": 61,
    "rating": 2.4
  },
  {
    "year": 2025,
    "team": "Mississippi State",
    "conference": "SEC",
    "division": null,
    "ranking": 62,
    "rating": 2.3
  },
  {
    "year": 2025,
    "team": "Wisconsin",
    "conference": "Big Ten",
    "division": null,
    "ranking": 62,
    "rating": 2.3
  },
  {
    "year": 2025,
    "team": "Navy",
    "conference": "American Athletic",
    "division": null,
    "ranking": 64,
    "rating": 2.1
  },
  {
    "year": 2025,
    "team": "North Dakota State",
    "conference": "MVFC",
    "division": null,
    "ranking": 65,
    "rating": 1.5
  },
  {
    "year": 2025,
    "team": "UTSA",
    "conference": "American Athletic",
    "division": null,
    "ranking": 65,
    "rating": 1.5
  },
  {
    "year": 2025,
    "team": "Minnesota",
    "conference": "Big Ten",
    "division": null,
    "ranking": 67,
    "rating": 0.7
  },
  {
    "year": 2025,
    "team": "Baylor",
    "conference": "Big 12",
    "division": null,
    "ranking": 68,
    "rating": 0.6
  },
  {
    "year": 2025,
    "team": "Western Michigan",
    "conference": "Mid-American",
    "division": null,
    "ranking": 69,
    "rating": -0.1
  },
  {
    "year": 2025,
    "team": "New Mexico",
    "conference": "Mountain West",
    "division": null,
    "ranking": 70,
    "rating": -0.2
  },
  {
    "year": 2025,
    "team": "Michigan State",
    "conference": "Big Ten",
    "division": null,
    "ranking": 71,
    "rating": -0.3
  },
  {
    "year": 2025,
    "team": "Maryland",
    "conference": "Big Ten",
    "division": null,
    "ranking": 72,
    "rating": -0.8
  },
  {
    "year": 2025,
    "team": "Army",
    "conference": "American Athletic",
    "division": null,
    "ranking": 72,
    "rating": -0.8
  },
  {
    "year": 2025,
    "team": "UCF",
    "conference": "Big 12",
    "division": null,
    "ranking": 72,
    "rating": -0.8
  },
  {
    "year": 2025,
    "team": "UNLV",
    "conference": "Mountain West",
    "division": null,
    "ranking": 75,
    "rating": -0.9
  },
  {
    "year": 2025,
    "team": "UCLA",
    "conference": "Big Ten",
    "division": null,
    "ranking": 76,
    "rating": -1.1
  },
  {
    "year": 2025,
    "team": "Purdue",
    "conference": "Big Ten",
    "division": null,
    "ranking": 77,
    "rating": -1.6
  },
  {
    "year": 2025,
    "team": "Texas State",
    "conference": "Sun Belt",
    "division": "West",
    "ranking": 77,
    "rating": -1.6
  },
  {
    "year": 2025,
    "team": "Montana State",
    "conference": "Big Sky",
    "division": null,
    "ranking": 79,
    "rating": -1.7
  },
  {
    "year": 2025,
    "team": "Utah State",
    "conference": "Mountain West",
    "division": null,
    "ranking": 80,
    "rating": -1.9
  },
  {
    "year": 2025,
    "team": "Colorado",
    "conference": "Big 12",
    "division": null,
    "ranking": 81,
    "rating": -2.2
  },
  {
    "year": 2025,
    "team": "West Virginia",
    "conference": "Big 12",
    "division": null,
    "ranking": 82,
    "rating": -2.6
  },
  {
    "year": 2025,
    "team": "Fresno State",
    "conference": "Mountain West",
    "division": null,
    "ranking": 83,
    "rating": -2.7
  },
  {
    "year": 2025,
    "team": "Hawai'i",
    "conference": "Mountain West",
    "division": null,
    "ranking": 84,
    "rating": -3.3
  },
  {
    "year": 2025,
    "team": "UConn",
    "conference": "FBS Independents",
    "division": null,
    "ranking": 85,
    "rating": -3.5
  },
  {
    "year": 2025,
    "team": "Ohio",
    "conference": "Mid-American",
    "division": null,
    "ranking": 85,
    "rating": -3.5
  },
  {
    "year": 2025,
    "team": "Louisiana Tech",
    "conference": "Conference USA",
    "division": null,
    "ranking": 87,
    "rating": -3.9
  },
  {
    "year": 2025,
    "team": "California",
    "conference": "ACC",
    "division": null,
    "ranking": 88,
    "rating": -4.1
  },
  {
    "year": 2025,
    "team": "Virginia Tech",
    "conference": "ACC",
    "division": null,
    "ranking": 88,
    "rating": -4.1
  },
  {
    "year": 2025,
    "team": "Stanford",
    "conference": "ACC",
    "division": null,
    "ranking": 88,
    "rating": -4.1
  },
  {
    "year": 2025,
    "team": "Western Kentucky",
    "conference": "Conference USA",
    "division": null,
    "ranking": 91,
    "rating": -4.2
  },
  {
    "year": 2025,
    "team": "Kennesaw State",
    "conference": "Conference USA",
    "division": null,
    "ranking": 92,
    "rating": -4.4
  },
  {
    "year": 2025,
    "team": "Boston College",
    "conference": "ACC",
    "division": null,
    "ranking": 93,
    "rating": -5.4
  },
  {
    "year": 2025,
    "team": "Miami (OH)",
    "conference": "Mid-American",
    "division": null,
    "ranking": 94,
    "rating": -5.6
  },
  {
    "year": 2025,
    "team": "Marshall",
    "conference": "Sun Belt",
    "division": "East",
    "ranking": 95,
    "rating": -5.8
  },
  {
    "year": 2025,
    "team": "Montana",
    "conference": "Big Sky",
    "division": null,
    "ranking": 96,
    "rating": -6.1
  },
  {
    "year": 2025,
    "team": "North Dakota",
    "conference": "MVFC",
    "division": null,
    "ranking": 97,
    "rating": -6.2
  },
  {
    "year": 2025,
    "team": "North Carolina",
    "conference": "ACC",
    "division": null,
    "ranking": 98,
    "rating": -6.7
  },
  {
    "year": 2025,
    "team": "Tarleton State",
    "conference": "UAC",
    "division": null,
    "ranking": 99,
    "rating": -7
  },
  {
    "year": 2025,
    "team": "Temple",
    "conference": "American Athletic",
    "division": null,
    "ranking": 99,
    "rating": -7
  },
  {
    "year": 2025,
    "team": "Syracuse",
    "conference": "ACC",
    "division": null,
    "ranking": 101,
    "rating": -7.1
  },
  {
    "year": 2025,
    "team": "Air Force",
    "conference": "Mountain West",
    "division": null,
    "ranking": 102,
    "rating": -7.4
  },
  {
    "year": 2025,
    "team": "Troy",
    "conference": "Sun Belt",
    "division": "West",
    "ranking": 103,
    "rating": -7.9
  },
  {
    "year": 2025,
    "team": "Central Michigan",
    "conference": "Mid-American",
    "division": null,
    "ranking": 104,
    "rating": -8.4
  },
  {
    "year": 2025,
    "team": "Jacksonville State",
    "conference": "Conference USA",
    "division": null,
    "ranking": 104,
    "rating": -8.4
  },
  {
    "year": 2025,
    "team": "Georgia Southern",
    "conference": "Sun Belt",
    "division": "East",
    "ranking": 106,
    "rating": -8.6
  },
  {
    "year": 2025,
    "team": "Southern Miss",
    "conference": "Sun Belt",
    "division": "West",
    "ranking": 106,
    "rating": -8.6
  },
  {
    "year": 2025,
    "team": "Missouri State",
    "conference": "Conference USA",
    "division": null,
    "ranking": 108,
    "rating": -8.8
  },
  {
    "year": 2025,
    "team": "Liberty",
    "conference": "Conference USA",
    "division": null,
    "ranking": 109,
    "rating": -10
  },
  {
    "year": 2025,
    "team": "Arkansas State",
    "conference": "Sun Belt",
    "division": "West",
    "ranking": 110,
    "rating": -10.2
  },
  {
    "year": 2025,
    "team": "Florida International",
    "conference": "Conference USA",
    "division": null,
    "ranking": 111,
    "rating": -10.4
  },
  {
    "year": 2025,
    "team": "Wyoming",
    "conference": "Mountain West",
    "division": null,
    "ranking": 112,
    "rating": -10.7
  },
  {
    "year": 2025,
    "team": "Florida Atlantic",
    "conference": "American Athletic",
    "division": null,
    "ranking": 113,
    "rating": -11.2
  },
  {
    "year": 2025,
    "team": "Oklahoma State",
    "conference": "Big 12",
    "division": null,
    "ranking": 114,
    "rating": -11.3
  },
  {
    "year": 2025,
    "team": "Tulsa",
    "conference": "American Athletic",
    "division": null,
    "ranking": 114,
    "rating": -11.3
  },
  {
    "year": 2025,
    "team": "Stephen F. Austin",
    "conference": "Southland",
    "division": null,
    "ranking": 116,
    "rating": -11.4
  },
  {
    "year": 2025,
    "team": "Coastal Carolina",
    "conference": "Sun Belt",
    "division": "East",
    "ranking": 117,
    "rating": -11.6
  },
  {
    "year": 2025,
    "team": "Louisiana",
    "conference": "Sun Belt",
    "division": "West",
    "ranking": 117,
    "rating": -11.6
  },
  {
    "year": 2025,
    "team": "Illinois State",
    "conference": "MVFC",
    "division": null,
    "ranking": 119,
    "rating": -11.7
  },
  {
    "year": 2025,
    "team": "Southern Illinois",
    "conference": "MVFC",
    "division": null,
    "ranking": 119,
    "rating": -11.7
  },
  {
    "year": 2025,
    "team": "App State",
    "conference": "Sun Belt",
    "division": "East",
    "ranking": 121,
    "rating": -12.2
  },
  {
    "year": 2025,
    "team": "South Dakota State",
    "conference": "MVFC",
    "division": null,
    "ranking": 121,
    "rating": -12.2
  },
  {
    "year": 2025,
    "team": "Delaware",
    "conference": "Conference USA",
    "division": null,
    "ranking": 123,
    "rating": -12.4
  },
  {
    "year": 2025,
    "team": "Oregon State",
    "conference": "Pac-12",
    "division": null,
    "ranking": 124,
    "rating": -12.6
  },
  {
    "year": 2025,
    "team": "South Alabama",
    "conference": "Sun Belt",
    "division": "West",
    "ranking": 125,
    "rating": -12.8
  },
  {
    "year": 2025,
    "team": "Nevada",
    "conference": "Mountain West",
    "division": null,
    "ranking": 126,
    "rating": -13.3
  },
  {
    "year": 2025,
    "team": "Abilene Christian",
    "conference": "UAC",
    "division": null,
    "ranking": 127,
    "rating": -13.5
  },
  {
    "year": 2025,
    "team": "Colorado State",
    "conference": "Mountain West",
    "division": null,
    "ranking": 128,
    "rating": -13.8
  },
  {
    "year": 2025,
    "team": "UC Davis",
    "conference": "Big Sky",
    "division": null,
    "ranking": 129,
    "rating": -14.1
  },
  {
    "year": 2025,
    "team": "Buffalo",
    "conference": "Mid-American",
    "division": null,
    "ranking": 130,
    "rating": -14.2
  },
  {
    "year": 2025,
    "team": "UAB",
    "conference": "American Athletic",
    "division": null,
    "ranking": 131,
    "rating": -14.3
  },
  {
    "year": 2025,
    "team": "San José State",
    "conference": "Mountain West",
    "division": null,
    "ranking": 132,
    "rating": -14.4
  },
  {
    "year": 2025,
    "team": "Bowling Green",
    "conference": "Mid-American",
    "division": null,
    "ranking": 132,
    "rating": -14.4
  },
  {
    "year": 2025,
    "team": "Lehigh",
    "conference": "Patriot",
    "division": null,
    "ranking": 134,
    "rating": -14.5
  },
  {
    "year": 2025,
    "team": "Akron",
    "conference": "Mid-American",
    "division": null,
    "ranking": 135,
    "rating": -14.6
  },
  {
    "year": 2025,
    "team": "South Dakota",
    "conference": "MVFC",
    "division": null,
    "ranking": 136,
    "rating": -14.7
  },
  {
    "year": 2025,
    "team": "Sacramento State",
    "conference": "Big Sky",
    "division": null,
    "ranking": 137,
    "rating": -14.8
  },
  {
    "year": 2025,
    "team": "Youngstown State",
    "conference": "MVFC",
    "division": null,
    "ranking": 138,
    "rating": -14.9
  },
  {
    "year": 2025,
    "team": "Idaho State",
    "conference": "Big Sky",
    "division": null,
    "ranking": 139,
    "rating": -15
  },
  {
    "year": 2025,
    "team": "Rice",
    "conference": "American Athletic",
    "division": null,
    "ranking": 140,
    "rating": -15.1
  },
  {
    "year": 2025,
    "team": "Yale",
    "conference": "Ivy",
    "division": null,
    "ranking": 141,
    "rating": -16.1
  },
  {
    "year": 2025,
    "team": "Kent State",
    "conference": "Mid-American",
    "division": null,
    "ranking": 141,
    "rating": -16.1
  },
  {
    "year": 2025,
    "team": "New Mexico State",
    "conference": "Conference USA",
    "division": null,
    "ranking": 141,
    "rating": -16.1
  },
  {
    "year": 2025,
    "team": "Eastern Michigan",
    "conference": "Mid-American",
    "division": null,
    "ranking": 144,
    "rating": -16.2
  },
  {
    "year": 2025,
    "team": "Austin Peay",
    "conference": "UAC",
    "division": null,
    "ranking": 144,
    "rating": -16.2
  },
  {
    "year": 2025,
    "team": "Villanova",
    "conference": "CAA",
    "division": null,
    "ranking": 146,
    "rating": -16.6
  },
  {
    "year": 2025,
    "team": "Southern Utah",
    "conference": "UAC",
    "division": null,
    "ranking": 147,
    "rating": -16.9
  },
  {
    "year": 2025,
    "team": "Harvard",
    "conference": "Ivy",
    "division": null,
    "ranking": 148,
    "rating": -17.2
  },
  {
    "year": 2025,
    "team": "Northern Illinois",
    "conference": "Mid-American",
    "division": null,
    "ranking": 148,
    "rating": -17.2
  },
  {
    "year": 2025,
    "team": "UTEP",
    "conference": "Conference USA",
    "division": null,
    "ranking": 150,
    "rating": -17.7
  },
  {
    "year": 2025,
    "team": "Georgia State",
    "conference": "Sun Belt",
    "division": "East",
    "ranking": 151,
    "rating": -18.1
  },
  {
    "year": 2025,
    "team": "Middle Tennessee",
    "conference": "Conference USA",
    "division": null,
    "ranking": 152,
    "rating": -18.4
  },
  {
    "year": 2025,
    "team": "SE Louisiana",
    "conference": "Southland",
    "division": null,
    "ranking": 153,
    "rating": -18.5
  },
  {
    "year": 2025,
    "team": "Tennessee Tech",
    "conference": "Big South-OVC",
    "division": null,
    "ranking": 153,
    "rating": -18.5
  },
  {
    "year": 2025,
    "team": "Ball State",
    "conference": "Mid-American",
    "division": null,
    "ranking": 155,
    "rating": -19.1
  },
  {
    "year": 2025,
    "team": "Northern Arizona",
    "conference": "Big Sky",
    "division": null,
    "ranking": 156,
    "rating": -19.4
  },
  {
    "year": 2025,
    "team": "UL Monroe",
    "conference": "Sun Belt",
    "division": "West",
    "ranking": 157,
    "rating": -20
  },
  {
    "year": 2025,
    "team": "West Georgia",
    "conference": "UAC",
    "division": null,
    "ranking": 158,
    "rating": -20.1
  },
  {
    "year": 2025,
    "team": "Mercer",
    "conference": "Southern",
    "division": null,
    "ranking": 159,
    "rating": -20.2
  },
  {
    "year": 2025,
    "team": "Rhode Island",
    "conference": "CAA",
    "division": null,
    "ranking": 159,
    "rating": -20.2
  },
  {
    "year": 2025,
    "team": "Idaho",
    "conference": "Big Sky",
    "division": null,
    "ranking": 161,
    "rating": -20.4
  },
  {
    "year": 2025,
    "team": "UT Rio Grande Valley",
    "conference": "Southland",
    "division": null,
    "ranking": 162,
    "rating": -20.5
  },
  {
    "year": 2025,
    "team": "Cal Poly",
    "conference": "Big Sky",
    "division": null,
    "ranking": 163,
    "rating": -21.6
  },
  {
    "year": 2025,
    "team": "Charlotte",
    "conference": null,
    "division": null,
    "ranking": 164,
    "rating": -21.8
  },
  {
    "year": 2025,
    "team": "Charlotte",
    "conference": "American Athletic",
    "division": null,
    "ranking": 164,
    "rating": -21.8
  },
  {
    "year": 2025,
    "team": "Alabama State",
    "conference": "SWAC",
    "division": "East",
    "ranking": 166,
    "rating": -22.1
  },
  {
    "year": 2025,
    "team": "Monmouth",
    "conference": "CAA",
    "division": null,
    "ranking": 167,
    "rating": -22.3
  },
  {
    "year": 2025,
    "team": "Sam Houston",
    "conference": "Conference USA",
    "division": null,
    "ranking": 168,
    "rating": -22.7
  },
  {
    "year": 2025,
    "team": "New Hampshire",
    "conference": "CAA",
    "division": null,
    "ranking": 169,
    "rating": -23.3
  },
  {
    "year": 2025,
    "team": "Lamar",
    "conference": "Southland",
    "division": null,
    "ranking": 170,
    "rating": -23.5
  },
  {
    "year": 2025,
    "team": "Eastern Washington",
    "conference": "Big Sky",
    "division": null,
    "ranking": 171,
    "rating": -23.9
  },
  {
    "year": 2025,
    "team": "Incarnate Word",
    "conference": "Southland",
    "division": null,
    "ranking": 172,
    "rating": -24.1
  },
  {
    "year": 2025,
    "team": "East Tennessee State",
    "conference": "Southern",
    "division": null,
    "ranking": 173,
    "rating": -24.6
  },
  {
    "year": 2025,
    "team": "Eastern Kentucky",
    "conference": "UAC",
    "division": null,
    "ranking": 174,
    "rating": -24.7
  },
  {
    "year": 2025,
    "team": "St. Thomas (MN)",
    "conference": "Pioneer",
    "division": null,
    "ranking": 175,
    "rating": -25.2
  },
  {
    "year": 2025,
    "team": "Dartmouth",
    "conference": "Ivy",
    "division": null,
    "ranking": 176,
    "rating": -25.4
  },
  {
    "year": 2025,
    "team": "Lafayette",
    "conference": "Patriot",
    "division": null,
    "ranking": 177,
    "rating": -26
  },
  {
    "year": 2025,
    "team": "Northern Colorado",
    "conference": "Big Sky",
    "division": null,
    "ranking": 178,
    "rating": -26.2
  },
  {
    "year": 2025,
    "team": "Drake",
    "conference": "Pioneer",
    "division": null,
    "ranking": 179,
    "rating": -26.4
  },
  {
    "year": 2025,
    "team": "South Carolina State",
    "conference": "MEAC",
    "division": null,
    "ranking": 180,
    "rating": -26.5
  },
  {
    "year": 2025,
    "team": "Western Carolina",
    "conference": "Southern",
    "division": null,
    "ranking": 181,
    "rating": -26.6
  },
  {
    "year": 2025,
    "team": "Northern Iowa",
    "conference": "MVFC",
    "division": null,
    "ranking": 182,
    "rating": -26.7
  },
  {
    "year": 2025,
    "team": "Wofford",
    "conference": "Southern",
    "division": null,
    "ranking": 182,
    "rating": -26.7
  },
  {
    "year": 2025,
    "team": "Jackson State",
    "conference": "SWAC",
    "division": "East",
    "ranking": 182,
    "rating": -26.7
  },
  {
    "year": 2025,
    "team": "Elon",
    "conference": "CAA",
    "division": null,
    "ranking": 185,
    "rating": -27
  },
  {
    "year": 2025,
    "team": "William & Mary",
    "conference": "CAA",
    "division": null,
    "ranking": 185,
    "rating": -27
  },
  {
    "year": 2025,
    "team": "Gardner-Webb",
    "conference": "Big South-OVC",
    "division": null,
    "ranking": 187,
    "rating": -27.3
  },
  {
    "year": 2025,
    "team": "Stony Brook",
    "conference": "CAA",
    "division": null,
    "ranking": 187,
    "rating": -27.3
  },
  {
    "year": 2025,
    "team": "Pennsylvania",
    "conference": "Ivy",
    "division": null,
    "ranking": 189,
    "rating": -27.4
  },
  {
    "year": 2025,
    "team": "Weber State",
    "conference": "Big Sky",
    "division": null,
    "ranking": 189,
    "rating": -27.4
  },
  {
    "year": 2025,
    "team": "Presbyterian",
    "conference": "Pioneer",
    "division": null,
    "ranking": 191,
    "rating": -27.7
  },
  {
    "year": 2025,
    "team": "UT Martin",
    "conference": "Big South-OVC",
    "division": null,
    "ranking": 192,
    "rating": -28.3
  },
  {
    "year": 2025,
    "team": "San Diego",
    "conference": "Pioneer",
    "division": null,
    "ranking": 192,
    "rating": -28.3
  },
  {
    "year": 2025,
    "team": "Prairie View A&M",
    "conference": "SWAC",
    "division": "West",
    "ranking": 194,
    "rating": -28.4
  },
  {
    "year": 2025,
    "team": "Lindenwood",
    "conference": "Big South-OVC",
    "division": null,
    "ranking": 195,
    "rating": -28.6
  },
  {
    "year": 2025,
    "team": "Maine",
    "conference": "CAA",
    "division": null,
    "ranking": 196,
    "rating": -28.7
  },
  {
    "year": 2025,
    "team": "Central Arkansas",
    "conference": "UAC",
    "division": null,
    "ranking": 197,
    "rating": -28.8
  },
  {
    "year": 2025,
    "team": "Nicholls",
    "conference": "Southland",
    "division": null,
    "ranking": 198,
    "rating": -28.9
  },
  {
    "year": 2025,
    "team": "Indiana State",
    "conference": "MVFC",
    "division": null,
    "ranking": 198,
    "rating": -28.9
  },
  {
    "year": 2025,
    "team": "Holy Cross",
    "conference": "Patriot",
    "division": null,
    "ranking": 200,
    "rating": -29.7
  },
  {
    "year": 2025,
    "team": "Princeton",
    "conference": "Ivy",
    "division": null,
    "ranking": 201,
    "rating": -29.8
  },
  {
    "year": 2025,
    "team": "Towson",
    "conference": "CAA",
    "division": null,
    "ranking": 202,
    "rating": -29.9
  },
  {
    "year": 2025,
    "team": "Brown",
    "conference": "Ivy",
    "division": null,
    "ranking": 203,
    "rating": -30.2
  },
  {
    "year": 2025,
    "team": "Central Connecticut",
    "conference": "NEC",
    "division": null,
    "ranking": 204,
    "rating": -30.4
  },
  {
    "year": 2025,
    "team": "McNeese",
    "conference": "Southland",
    "division": null,
    "ranking": 205,
    "rating": -30.6
  },
  {
    "year": 2025,
    "team": "North Carolina Central",
    "conference": "MEAC",
    "division": null,
    "ranking": 206,
    "rating": -30.8
  },
  {
    "year": 2025,
    "team": "Colgate",
    "conference": "Patriot",
    "division": null,
    "ranking": 207,
    "rating": -30.9
  },
  {
    "year": 2025,
    "team": "The Citadel",
    "conference": "Southern",
    "division": null,
    "ranking": 208,
    "rating": -31
  },
  {
    "year": 2025,
    "team": "Richmond",
    "conference": "Patriot",
    "division": null,
    "ranking": 209,
    "rating": -31.5
  },
  {
    "year": 2025,
    "team": "Delaware State",
    "conference": "MEAC",
    "division": null,
    "ranking": 210,
    "rating": -31.6
  },
  {
    "year": 2025,
    "team": "Charleston Southern",
    "conference": "Big South-OVC",
    "division": null,
    "ranking": 211,
    "rating": -31.9
  },
  {
    "year": 2025,
    "team": "Southeast Missouri State",
    "conference": "Big South-OVC",
    "division": null,
    "ranking": 212,
    "rating": -32
  },
  {
    "year": 2025,
    "team": "Massachusetts",
    "conference": "Mid-American",
    "division": null,
    "ranking": 213,
    "rating": -32.3
  },
  {
    "year": 2025,
    "team": "Sacred Heart",
    "conference": "FCS Independents",
    "division": null,
    "ranking": 214,
    "rating": -32.5
  },
  {
    "year": 2025,
    "team": "Dayton",
    "conference": "Pioneer",
    "division": null,
    "ranking": 215,
    "rating": -32.7
  },
  {
    "year": 2025,
    "team": "Duquesne",
    "conference": "NEC",
    "division": null,
    "ranking": 215,
    "rating": -32.7
  },
  {
    "year": 2025,
    "team": "North Alabama",
    "conference": "UAC",
    "division": null,
    "ranking": 217,
    "rating": -33
  },
  {
    "year": 2025,
    "team": "Utah Tech",
    "conference": "UAC",
    "division": null,
    "ranking": 218,
    "rating": -33.3
  },
  {
    "year": 2025,
    "team": "Long Island University",
    "conference": "NEC",
    "division": null,
    "ranking": 219,
    "rating": -33.5
  },
  {
    "year": 2025,
    "team": "Mercyhurst",
    "conference": "NEC",
    "division": null,
    "ranking": 220,
    "rating": -33.6
  },
  {
    "year": 2025,
    "team": "Furman",
    "conference": "Southern",
    "division": null,
    "ranking": 221,
    "rating": -33.7
  },
  {
    "year": 2025,
    "team": "East Texas A&M",
    "conference": "Southland",
    "division": null,
    "ranking": 222,
    "rating": -34
  },
  {
    "year": 2025,
    "team": "Chattanooga",
    "conference": "Southern",
    "division": null,
    "ranking": 223,
    "rating": -34.2
  },
  {
    "year": 2025,
    "team": "Cornell",
    "conference": "Ivy",
    "division": null,
    "ranking": 223,
    "rating": -34.2
  },
  {
    "year": 2025,
    "team": "Portland State",
    "conference": "Big Sky",
    "division": null,
    "ranking": 225,
    "rating": -34.7
  },
  {
    "year": 2025,
    "team": "Merrimack",
    "conference": "FCS Independents",
    "division": null,
    "ranking": 226,
    "rating": -34.9
  },
  {
    "year": 2025,
    "team": "Murray State",
    "conference": "MVFC",
    "division": null,
    "ranking": 227,
    "rating": -35.2
  },
  {
    "year": 2025,
    "team": "Western Illinois",
    "conference": "Big South-OVC",
    "division": null,
    "ranking": 228,
    "rating": -35.3
  },
  {
    "year": 2025,
    "team": "Bethune-Cookman",
    "conference": "SWAC",
    "division": "East",
    "ranking": 229,
    "rating": -36.4
  },
  {
    "year": 2025,
    "team": "Columbia",
    "conference": "Ivy",
    "division": null,
    "ranking": 230,
    "rating": -36.7
  },
  {
    "year": 2025,
    "team": "Marist",
    "conference": "Pioneer",
    "division": null,
    "ranking": 231,
    "rating": -36.9
  },
  {
    "year": 2025,
    "team": "Campbell",
    "conference": "CAA",
    "division": null,
    "ranking": 232,
    "rating": -37
  },
  {
    "year": 2025,
    "team": "Butler",
    "conference": "Pioneer",
    "division": null,
    "ranking": 232,
    "rating": -37
  },
  {
    "year": 2025,
    "team": "Eastern Illinois",
    "conference": "Big South-OVC",
    "division": null,
    "ranking": 234,
    "rating": -37.1
  },
  {
    "year": 2025,
    "team": "Georgetown",
    "conference": "Patriot",
    "division": null,
    "ranking": 235,
    "rating": -38.6
  },
  {
    "year": 2025,
    "team": "UAlbany",
    "conference": "CAA",
    "division": null,
    "ranking": 236,
    "rating": -38.7
  },
  {
    "year": 2025,
    "team": "Texas Southern",
    "conference": "SWAC",
    "division": "West",
    "ranking": 237,
    "rating": -38.9
  },
  {
    "year": 2025,
    "team": "Bryant",
    "conference": "CAA",
    "division": null,
    "ranking": 238,
    "rating": -39
  },
  {
    "year": 2025,
    "team": "Grambling",
    "conference": "SWAC",
    "division": "West",
    "ranking": 239,
    "rating": -39.1
  },
  {
    "year": 2025,
    "team": "Morgan State",
    "conference": "MEAC",
    "division": null,
    "ranking": 240,
    "rating": -39.4
  },
  {
    "year": 2025,
    "team": "Stonehill",
    "conference": "NEC",
    "division": null,
    "ranking": 241,
    "rating": -39.5
  },
  {
    "year": 2025,
    "team": "Bucknell",
    "conference": "Patriot",
    "division": null,
    "ranking": 242,
    "rating": -39.9
  },
  {
    "year": 2025,
    "team": "Alcorn State",
    "conference": "SWAC",
    "division": "West",
    "ranking": 243,
    "rating": -40.2
  },
  {
    "year": 2025,
    "team": "Wagner",
    "conference": "NEC",
    "division": null,
    "ranking": 244,
    "rating": -40.4
  },
  {
    "year": 2025,
    "team": "Robert Morris",
    "conference": "NEC",
    "division": null,
    "ranking": 245,
    "rating": -41.8
  },
  {
    "year": 2025,
    "team": "Howard",
    "conference": "MEAC",
    "division": null,
    "ranking": 246,
    "rating": -41.9
  },
  {
    "year": 2025,
    "team": "Houston Christian",
    "conference": "Southland",
    "division": null,
    "ranking": 247,
    "rating": -42.6
  },
  {
    "year": 2025,
    "team": "Tennessee State",
    "conference": "Big South-OVC",
    "division": null,
    "ranking": 248,
    "rating": -42.7
  },
  {
    "year": 2025,
    "team": "Samford",
    "conference": "Southern",
    "division": null,
    "ranking": 249,
    "rating": -43.5
  },
  {
    "year": 2025,
    "team": "Morehead State",
    "conference": "Pioneer",
    "division": null,
    "ranking": 250,
    "rating": -43.8
  },
  {
    "year": 2025,
    "team": "Fordham",
    "conference": "Patriot",
    "division": null,
    "ranking": 251,
    "rating": -43.9
  },
  {
    "year": 2025,
    "team": "Alabama A&M",
    "conference": "SWAC",
    "division": "East",
    "ranking": 252,
    "rating": -44.5
  },
  {
    "year": 2025,
    "team": "North Carolina A&T",
    "conference": "CAA",
    "division": null,
    "ranking": 253,
    "rating": -46.1
  },
  {
    "year": 2025,
    "team": "Northwestern State",
    "conference": "Southland",
    "division": null,
    "ranking": 254,
    "rating": -46.2
  },
  {
    "year": 2025,
    "team": "Florida A&M",
    "conference": "SWAC",
    "division": "East",
    "ranking": 255,
    "rating": -46.3
  },
  {
    "year": 2025,
    "team": "New Haven",
    "conference": "NEC",
    "division": null,
    "ranking": 255,
    "rating": -46.3
  },
  {
    "year": 2025,
    "team": "Norfolk State",
    "conference": "MEAC",
    "division": null,
    "ranking": 257,
    "rating": -47
  },
  {
    "year": 2025,
    "team": "Arkansas-Pine Bluff",
    "conference": "SWAC",
    "division": "West",
    "ranking": 258,
    "rating": -47.7
  },
  {
    "year": 2025,
    "team": "VMI",
    "conference": "Southern",
    "division": null,
    "ranking": 259,
    "rating": -48
  },
  {
    "year": 2025,
    "team": "St. Francis (PA)",
    "conference": "NEC",
    "division": null,
    "ranking": 260,
    "rating": -49.2
  },
  {
    "year": 2025,
    "team": "Hampton",
    "conference": "CAA",
    "division": null,
    "ranking": 261,
    "rating": -49.4
  },
  {
    "year": 2025,
    "team": "Mississippi Valley State",
    "conference": "SWAC",
    "division": "East",
    "ranking": 262,
    "rating": -50.4
  },
  {
    "year": 2025,
    "team": "Valparaiso",
    "conference": "Pioneer",
    "division": null,
    "ranking": 262,
    "rating": -50.4
  },
  {
    "year": 2025,
    "team": "Southern",
    "conference": "SWAC",
    "division": "West",
    "ranking": 264,
    "rating": -51.6
  },
  {
    "year": 2025,
    "team": "Davidson",
    "conference": "Pioneer",
    "division": null,
    "ranking": 265,
    "rating": -51.8
  },
  {
    "year": 2025,
    "team": "Stetson",
    "conference": "Pioneer",
    "division": null,
    "ranking": 266,
    "rating": -53.5
  }
]